Workbook
Name aaa: #REF!
Name ACTIONLOG: {1,2,3,4,5,6,7;"M","T","W","T","F","S","S"}
Name Assumptions: #REF!
Name BLPG_ex_works_4020_€_Non_Oil_mtrls_plus: #REF!
Name BLPG_ex_works_4020_€_Pricelist_plus: #REF!
Name Bob: #REF!
Name ColorStatusIndicators: #REF!
Name Countries: #REF!
Name CurrentQuarter: #REF!
Name cvp: #REF!
Name Day_lookup: {1,2,3,4,5,6,7;"M","T","W","T","F","S","S"}
Name DiscountRate: #REF!
Name ex: #REF!
Name FX: #REF!
Name G: #REF!
Name grades: #REF!
Name GRCs: #REF!
Name Manuf_Antwerp: #REF!
Name Manuf_Hyde: #REF!
Name Manuf_Stanlow: #REF!
Name NumberStatus: #REF!
Name NumberStatusIndicators: #REF!
Name P: #REF!
Name pivot: #REF!
Name Plan16nocapex: #REF!
Name PRINTS: #REF!
Name RM: #REF!
Name SC_Summary: #REF!
Name SChain_BE: #REF!
Name SChain_DK: #REF!
Name SChain_IR: #REF!
Name SChain_NOR: #REF!
Name SChain_SWE: #REF!
Name SChain_UK: #REF!
Name SEVERITY: #REF!
Name stage: #REF!
Name Start_Date: #REF!
Name StatusIndicators: #REF!
Name StatusNumber: #REF!
Name Tax_GRE: #REF!
Name Tax_RoE: #REF!
Name TemporaryPermanent: #REF!
Name ThreeStatusNumber: #REF!
Name Todays_Date: #REF!
Name WHNoMonths: #REF!

Sheet DS Reconciliation
A1: DS RECONCILIATION · Payroll vs Scorecard | H1: Period: | J1: AP09 | K1: Year: | L1: 2026 | M1: SC date: | N1: ="01/"&RIGHT($J$1,2)&"/"&$L$1 -> 01/09/2026
A2: Process | B2: ="Payroll FTE "&$J$1 -> Payroll FTE AP09 | C2: Vacancy | D2: Sick leave | E2: Adjustment | F2: FTE Real | G2: FTE Scorecard | I2: AP Clerk | J2: TL | K2: Mng. | L2: H. Desk | M2: Bank. | N2: Difference | O2: Status | P2: Comments | T2: BSC
A3: P2P | B3: =SUM(B4:B8) -> 14.3125 | C3: =+SUM(C4:C8) -> 2 | D3: =+SUM(D4:D8) -> 3 | E3: =+SUM(E4:E8) -> 1.8 | F3: =+B3+C3-D3-E3 -> 11.5125 | G3: =SUM(G9:G17) -> 50.07 | H3: Breakdown >> | I3: =+SUM(I9:I17) -> 31.14 | J3: =+SUM(J9:J17) -> 7 | K3: =+SUM(K9:K17) -> 2 | L3: =+SUM(L9:L17) -> 6.5 | M3: =+SUM(M9:M17) -> 4.0049312 | N3: =G3-F3 -> 38.5575 | O3: =IF(N(G3)=0,"",IF(ABS(N3)<=0.02,"OK","Review")) -> Review | S3: Banking - Collections | T3: 3
A4: AP Continuos improvement | B4: =SUMIFS(Payroll!$I:$I,Payroll!$D:$D,$J$1,Payroll!$H:$H,"DSS",Payroll!$F:$F,"P2P*",Payroll!$K:$K,$A4) -> 1 | D4: 0 | F4: =+B4+C4-D4-E4 -> 1 | G4: 1 | N4: =G4-F4 -> 0 | O4: =IF(N(G4)=0,"",IF(ABS(N4)<=0.02,"OK","Review")) -> OK | S4: Banking - Payment | T4: 5
A5: AP Help Desk | B5: =SUMIFS(Payroll!$I:$I,Payroll!$D:$D,$J$1,Payroll!$H:$H,"DSS",Payroll!$F:$F,"P2P*",Payroll!$K:$K,$A5) -> 1 | D5: 1 | E5: 0.5 | F5: =+B5+C5-D5-E5 -> -0.5 | G5: =SUM(L9:L17) -> 6.5 | N5: =G5-F5 -> 7 | O5: =IF(N(G5)=0,"",IF(ABS(N5)<=0.02,"OK","Review")) -> Review | S5: Banking - Treasury | T5: 2
A6: Banking | B6: =SUMIFS(Payroll!$I:$I,Payroll!$D:$D,$J$1,Payroll!$H:$H,"DSS",Payroll!$F:$F,"P2P*",Payroll!$K:$K,$A6) -> 1 | D6: 0 | E6: 1 | F6: =+B6+C6-D6-E6 -> 0 | G6: =+SUM(M9:M17) -> 4.0049312 | N6: =G6-F6 -> 4.0049312 | O6: =IF(N(G6)=0,"",IF(ABS(N6)<=0.02,"OK","Review")) -> Review | T6: =SUM(T3:T5) -> 10
A7: AP General | B7: =SUMIFS(Payroll!$I:$I,Payroll!$D:$D,$J$1,Payroll!$H:$H,"DSS",Payroll!$F:$F,"P2P*",Payroll!$K:$K,$A7) -> 1 | D7: 0 | F7: =+B7+C7-D7-E7 -> 1 | G7: 1 | N7: =G7-F7 -> 0 | O7: =IF(N(G7)=0,"",IF(ABS(N7)<=0.02,"OK","Review")) -> OK
A8: AP Total Clerk+TL | B8: =+SUM(B9:B17) -> 10.3125 | C8: =+SUM(C9:C17) -> 2 | D8: =+SUM(D9:D17) -> 2 | E8: =+SUM(E9:E17) -> 0.3 | F8: =+B8+C8-D8-E8 -> 10.0125 | G8: =+SUM(I9:J17) -> 38.14 | N8: =G8-F8 -> 28.1275 | O8: =IF(N(G8)=0,"",IF(ABS(N8)<=0.02,"OK","Review")) -> Review
A9: AP DE | B9: =SUMIFS(Payroll!$I:$I,Payroll!$D:$D,$J$1,Payroll!$H:$H,"DSS",Payroll!$F:$F,"P2P*",Payroll!$K:$K,$A9) -> 0 | D9: 0 | F9: =+B9+C9-D9-E9 -> 0 | G9: =SUMIFS('FTE Scorecard'!$F:$F,'FTE Scorecard'!$A:$A,"Total AP FTEs*",'FTE Scorecard'!$D:$D,TRIM(MID($A9,4,10)),'FTE Scorecard'!$E:$E,$N$1) -> 4.32 | I9: 3 | J9: 0.5 | K9: 0.18353435 | L9: 0.45 | M9: 0.18784404 | N9: =+SUM(I9:J9)-F9 -> 3.5 | O9: =IF(N(G9)=0,"",IF(ABS(N9)<=0.02,"OK","Review")) -> Review
A10: AP FR | B10: =SUMIFS(Payroll!$I:$I,Payroll!$D:$D,$J$1,Payroll!$H:$H,"DSS",Payroll!$F:$F,"P2P*",Payroll!$K:$K,$A10) -> 1.3125 | D10: 1 | F10: =+B10+C10-D10-E10 -> 0.3125 | G10: =SUMIFS('FTE Scorecard'!$F:$F,'FTE Scorecard'!$A:$A,"Total AP FTEs*",'FTE Scorecard'!$D:$D,TRIM(MID($A10,4,10)),'FTE Scorecard'!$E:$E,$N$1) -> 10.63 | I10: 7.81 | J10: 1 | K10: 0.46198217 | L10: 1.3 | M10: 0.63520642 | N10: =+(SUM(I10:J10)-F10) -> 8.4975 | O10: =IF(N(G10)=0,"",IF(ABS(N10)<=0.02,"OK","Review")) -> Review
A11: AP IB | B11: =SUMIFS(Payroll!$I:$I,Payroll!$D:$D,$J$1,Payroll!$H:$H,"DSS",Payroll!$F:$F,"P2P*",Payroll!$K:$K,$A11) -> 8 | D11: 0 | E11: 0.3 | F11: =+B11+C11-D11-E11 -> 7.7 | G11: =SUMIFS('FTE Scorecard'!$F:$F,'FTE Scorecard'!$A:$A,"Total AP FTEs*",'FTE Scorecard'!$D:$D,TRIM(MID($A11,4,10)),'FTE Scorecard'!$E:$E,$N$1) -> 10.19 | I11: 5.7 | J11: 2 | K11: 0.40377556 | L11: 1.2 | M11: 0.88979358 | N11: =+(SUM(I11:J11)-F11) -> 0 | O11: =IF(N(G11)=0,"",IF(ABS(N11)<=0.02,"OK","Review")) -> OK
A12: AP UK | B12: =SUMIFS(Payroll!$I:$I,Payroll!$D:$D,$J$1,Payroll!$H:$H,"DSS",Payroll!$F:$F,"P2P*",Payroll!$K:$K,$A12) -> 0 | C12: 1 | D12: 0 | F12: =+B12+C12-D12-E12 -> 1 | G12: =SUMIFS('FTE Scorecard'!$F:$F,'FTE Scorecard'!$A:$A,"Total AP FTEs*",'FTE Scorecard'!$D:$D,TRIM(MID($A12,4,10)),'FTE Scorecard'!$E:$E,$N$1) -> 10 | I12: 6 | J12: 0.5 | K12: 0.3408495 | L12: 2 | M12: 1.1596617 | N12: =+(SUM(I12:J14)-F12) -> 8 | O12: =IF(N(G12)=0,"",IF(ABS(N12)<=0.02,"OK","Review")) -> Review
A13: AP TMS | B13: =SUMIFS(Payroll!$I:$I,Payroll!$D:$D,$J$1,Payroll!$H:$H,"DSS",Payroll!$F:$F,"P2P*",Payroll!$K:$K,$A13) -> 0 | D13: 0 | F13: =+B13+C13-D13-E13 -> 0 | G13: =SUMIFS('FTE Scorecard'!$F:$F,'FTE Scorecard'!$A:$A,"Total AP FTEs*",'FTE Scorecard'!$D:$D,TRIM(MID($A13,4,10)),'FTE Scorecard'!$E:$E,$N$1) -> 2 | I13: 1 | J13: 0.25 | K13: 0.065547981 | L13: 0.5 | M13: 0.18043578 | N13: - | P13: Incluidos en UK
A14: AP PMS | B14: =SUMIFS(Payroll!$I:$I,Payroll!$D:$D,$J$1,Payroll!$H:$H,"DSS",Payroll!$F:$F,"P2P*",Payroll!$K:$K,$A14) -> 0 | D14: 0 | F14: =+B14+C14-D14-E14 -> 0 | G14: =SUMIFS('FTE Scorecard'!$F:$F,'FTE Scorecard'!$A:$A,"Total AP FTEs*",'FTE Scorecard'!$D:$D,TRIM(MID($A14,4,10)),'FTE Scorecard'!$E:$E,$N$1) -> 1.75 | I14: 1 | J14: 0.25 | K14: 0.065547981 | L14: 0.25 | M14: 0.18 | N14: - | P14: Incluidos en UK
A15: AP IT | B15: =SUMIFS(Payroll!$I:$I,Payroll!$D:$D,$J$1,Payroll!$H:$H,"DSS",Payroll!$F:$F,"P2P*",Payroll!$K:$K,$A15) -> 1 | D15: 0 | F15: =+B15+C15-D15-E15 -> 1 | G15: =SUMIFS('FTE Scorecard'!$F:$F,'FTE Scorecard'!$A:$A,"Total AP FTEs*",'FTE Scorecard'!$D:$D,TRIM(MID($A15,4,10)),'FTE Scorecard'!$E:$E,$N$1) -> 1.79 | I15: 1 | J15: 0.5 | K15: 0.078657577 | L15: 0.05 | M15: 0.16100917 | N15: =+(SUM(I15:J15)-F15) -> 0.5 | O15: =IF(N(G15)=0,"",IF(ABS(N15)<=0.02,"OK","Review")) -> Review
A16: AP BE | B16: =SUMIFS(Payroll!$I:$I,Payroll!$D:$D,$J$1,Payroll!$H:$H,"DSS",Payroll!$F:$F,"P2P*",Payroll!$K:$K,$A16) -> 0 | C16: 1 | D16: 0 | F16: =+B16+C16-D16-E16 -> 1 | G16: =SUMIFS('FTE Scorecard'!$F:$F,'FTE Scorecard'!$A:$A,"Total AP FTEs*",'FTE Scorecard'!$D:$D,TRIM(MID($A16,4,10)),'FTE Scorecard'!$E:$E,$N$1) -> 4.89 | I16: 3 | J16: 1 | K16: 0.20975354 | L16: 0.5 | M16: 0.18491972 | N16: =+(SUM(I16:J16)-F16) -> 3 | O16: =IF(N(G16)=0,"",IF(ABS(N16)<=0.02,"OK","Review")) -> Review
A17: AP PS | B17: =SUMIFS(Payroll!$I:$I,Payroll!$D:$D,$J$1,Payroll!$H:$H,"DSS",Payroll!$F:$F,"P2P*",Payroll!$K:$K,$A17) -> 0 | D17: 1 | F17: =+B17+C17-D17-E17 -> -1 | G17: =SUMIFS('FTE Scorecard'!$F:$F,'FTE Scorecard'!$A:$A,"Total AP FTEs*",'FTE Scorecard'!$D:$D,TRIM(MID($A17,4,10)),'FTE Scorecard'!$E:$E,$N$1) -> 4.5 | I17: 2.63 | J17: 1 | K17: 0.19035134 | L17: 0.25 | M17: 0.42606078 | N17: =+(SUM(I17:J17)-F17) -> 4.63 | O17: =IF(N(G17)=0,"",IF(ABS(N17)<=0.02,"OK","Review")) -> Review
A20: AR | B20: =SUM(B21:B23) -> 19 | C20: =+SUM(C21:C23) -> 0 | D20: =+SUM(D21:D23) -> 0 | E20: =+SUM(E21:E23) -> 0 | F20: =+B20+C20-D20-E20 -> 19 | G20: =SUMIFS('FTE Scorecard'!$F:$F,'FTE Scorecard'!$A:$A,"Total AR FTEs*",'FTE Scorecard'!$E:$E,$N$1) -> 23.1 | N20: =G20-F20 -> 4.1 | O20: =IF(N(G20)=0,"",IF(ABS(N20)<=0.02,"OK","Review")) -> Review
A21: AR Continuos improvement | B21: =SUMIFS(Payroll!$I:$I,Payroll!$D:$D,$J$1,Payroll!$H:$H,"DSS",Payroll!$F:$F,"Q2C",Payroll!$J:$J,"Mejora") -> 1 | F21: =+B21+C21-D21-E21 -> 1 | G21: 1 | N21: =G21-F21 -> 0 | O21: =IF(N(G21)=0,"",IF(ABS(N21)<=0.02,"OK","Review")) -> OK
A22: AR Banking | B22: =SUMIFS(Payroll!$I:$I,Payroll!$D:$D,$J$1,Payroll!$H:$H,"DSS",Payroll!$F:$F,"Q2C",Payroll!$G:$G,"Banking") -> 2 | F22: =+B22+C22-D22-E22 -> 2 | G22: 2 | N22: =G22-F22 -> 0 | O22: =IF(N(G22)=0,"",IF(ABS(N22)<=0.02,"OK","Review")) -> OK
A23: AR Clerk+TL | B23: =SUMIFS(Payroll!$I:$I,Payroll!$D:$D,$J$1,Payroll!$H:$H,"DSS",Payroll!$F:$F,"Q2C")-B21-B22 -> 16 | F23: =+B23+C23-D23-E23 -> 16 | G23: 16 | N23: =G23-F23 -> 0 | O23: =IF(N(G23)=0,"",IF(ABS(N23)<=0.02,"OK","Review")) -> OK
A25: R2R | B25: =SUM(B26:B28) -> 25.625 | C25: =+SUM(C26:C28) -> 1 | D25: =+SUM(D26:D28) -> 0 | E25: =+SUM(E26:E28) -> 5 | F25: =+B25+C25-D25-E25 -> 21.625 | G25: =SUMIFS('FTE Scorecard'!$F:$F,'FTE Scorecard'!$A:$A,"Total R2R*",'FTE Scorecard'!$E:$E,$N$1) -> 0 | N25: =G25-F25 -> -21.625 | O25: =IF(N(G25)=0,"",IF(ABS(N25)<=0.02,"OK","Review"))
A26: R2R Continuos improvement | B26: =SUMIFS(Payroll!$I:$I,Payroll!$D:$D,$J$1,Payroll!$H:$H,"DSS",Payroll!$F:$F,"R2R",Payroll!$J:$J,"Mejora") -> 0 | F26: =+B26+C26-D26-E26 -> 0 | G26: 0 | N26: =G26-F26 -> 0 | O26: =IF(N(G26)=0,"",IF(ABS(N26)<=0.02,"OK","Review"))
A27: R2R Banking | B27: =SUMIFS(Payroll!$I:$I,Payroll!$D:$D,$J$1,Payroll!$H:$H,"DSS",Payroll!$F:$F,"R2R",Payroll!$G:$G,"Banking") -> 2 | F27: =+B27+C27-D27-E27 -> 2 | G27: 2 | N27: =G27-F27 -> 0 | O27: =IF(N(G27)=0,"",IF(ABS(N27)<=0.02,"OK","Review")) -> OK
A28: R2R Junior+Senior | B28: =SUMIFS(Payroll!$I:$I,Payroll!$D:$D,$J$1,Payroll!$H:$H,"DSS",Payroll!$F:$F,"R2R")-B26-B27 -> 23.625 | C28: 1 | E28: 5 | F28: =+B28+C28-D28-E28 -> 19.625 | G28: 18.75 | N28: =G28-F28 -> -0.875 | O28: =IF(N(G28)=0,"",IF(ABS(N28)<=0.02,"OK","Review")) -> Review
A30: HR | B30: =SUMIFS(Payroll!$I:$I,Payroll!$D:$D,$J$1,Payroll!$H:$H,"DSS",Payroll!$F:$F,"HR") -> 1 | F30: =+B30+C30-D30-E30 -> 1 | G30: 1 | N30: =G30-F30 -> 0 | O30: =IF(N(G30)=0,"",IF(ABS(N30)<=0.02,"OK","Review")) -> OK
A32: MD | B32: =SUMIFS(Payroll!$I:$I,Payroll!$D:$D,$J$1,Payroll!$H:$H,"DSS",Payroll!$F:$F,"DM") -> 3 | F32: =+B32+C32-D32-E32 -> 3 | G32: 3 | N32: =G32-F32 -> 0 | O32: =IF(N(G32)=0,"",IF(ABS(N32)<=0.02,"OK","Review")) -> OK
A34: Subtotal (processes above) | B34: =B3+B20+B25+B30+B32 -> 62.9375 | C34: =C3+C20+C25+C30+C32 -> 3 | D34: =D3+D20+D25+D30+D32 -> 3 | E34: =E3+E20+E25+E30+E32 -> 6.8 | F34: =+B34+C34-D34-E34 -> 56.1375 | G34: =+G3+G20+G25+G30+G32 -> 77.17 | N34: =G34-F34 -> 21.0325 | O34: =IF(N(G34)=0,"",IF(ABS(N34)<=0.02,"OK","Review")) -> Review
A35: Out of scope (OoS) | B35: =SUMIFS(Payroll!$I:$I,Payroll!$D:$D,$J$1,Payroll!$H:$H,"DSS",Payroll!$F:$F,"OoS") -> 0
A36: TOTAL PAYROLL (DSS) | B36: =SUMIFS(Payroll!$I:$I,Payroll!$D:$D,$J$1,Payroll!$H:$H,"DSS") -> 104.375
A37: Unexplained difference | B37: =B36-B34-B35 -> 41.4375 | O37: =IF(ABS(B37)<=0.02,"OK","Review") -> Review
A39: ="Payroll rows in use: "&TEXT(COUNTA(Payroll!$D:$D)-1,"#,##0")&IF(COUNTA(Payroll!$D:$D)-1>4999," ⚠ Beyond row 5000: drag column K of Payroll further down."," · DSS "&TEXT(SUMIFS(Payroll!$I:$I,Payroll!$D:$D,$J$1,Payroll!$H:$H,"DSS"),"#,##0.00")&" + IP "&TEXT(SUMIFS(Payroll!$I:$I,Payroll!$D:$D,$J$1,Payroll!$H:$H,"IP"),"#,##0.00")&" + other business "&TEXT(SUMIFS(Payroll!$I:$I,Payroll!$D:$D,$J$1)-SUMIFS(Payroll!$I:$I,Payroll!$D:$D,$J$1,Payroll!$H:$H,"DSS")-SUMIFS(Payroll!$I:$I,Payroll!$D:$D,$J$1,Payroll!$H:$H,"IP"),"#,##0.00")&" = "&TEXT(SUMIFS(Payroll!$I:$I,Payroll!$D:$D,$J$1),"#,##0.00")&" · unmapped: "&TEXT(COUNTIF(Payroll!$K:$K,"(unmapped)"),"0")) -> Payroll rows in use: 180,0 · DSS 104,37500 + IP 65,47500 + other business 3,000 = 172,85000 · unmapped: 0

Sheet IP Reconciliation
A1: IP RECONCILIATION · Payroll vs Scorecard | D1: Period: | F1: AP09 | G1: Year: | H1: 2026 | I1: SC date: | J1: ="01/"&RIGHT($F$1,2)&"/"&$H$1 -> 01/09/2026
A2: Item | B2: Payroll FTE | C2: Vacancy | D2: Sick leave | E2: Adjustment | F2: FTE Real | G2: FTE Scorecard | H2: Difference | I2: Status | J2: Comments
A3: P2P | B3: =SUM(B4:B9) -> 23.8 | F3: =+B3+C3-D3-E3 -> 23.8 | G3: =+B3 -> 23.8 | H3: =+G3-F3 -> 0 | I3: =IF(N(G3)=0,"",IF(ABS(H3)<=0.02,"OK","Review")) -> OK
A4: AP IB | B4: =SUMIFS(Payroll!$I:$I,Payroll!$D:$D,$F$1,Payroll!$H:$H,"IP",Payroll!$F:$F,"P2P*",Payroll!$K:$K,$A4) -> 7 | F4: =+B4+C4-D4-E4 -> 7 | G4: =+B4 -> 7 | H4: =+G4-F4 -> 0 | I4: =IF(N(G4)=0,"",IF(ABS(H4)<=0.02,"OK","Review")) -> OK
A5: AP FR | B5: =SUMIFS(Payroll!$I:$I,Payroll!$D:$D,$F$1,Payroll!$H:$H,"IP",Payroll!$F:$F,"P2P*",Payroll!$K:$K,$A5) -> 1.8 | F5: =+B5+C5-D5-E5 -> 1.8 | G5: =+B5 -> 1.8 | H5: =+G5-F5 -> 0 | I5: =IF(N(G5)=0,"",IF(ABS(H5)<=0.02,"OK","Review")) -> OK
A6: AP IT | B6: =SUMIFS(Payroll!$I:$I,Payroll!$D:$D,$F$1,Payroll!$H:$H,"IP",Payroll!$F:$F,"P2P*",Payroll!$K:$K,$A6) -> 4 | F6: =+B6+C6-D6-E6 -> 4 | G6: =+B6 -> 4 | H6: =+G6-F6 -> 0 | I6: =IF(N(G6)=0,"",IF(ABS(H6)<=0.02,"OK","Review")) -> OK
A7: AP MA | B7: =SUMIFS(Payroll!$I:$I,Payroll!$D:$D,$F$1,Payroll!$H:$H,"IP",Payroll!$F:$F,"P2P*",Payroll!$K:$K,$A7) -> 7 | F7: =+B7+C7-D7-E7 -> 7 | G7: =+B7 -> 7 | H7: =+G7-F7 -> 0 | I7: =IF(N(G7)=0,"",IF(ABS(H7)<=0.02,"OK","Review")) -> OK
A8: AP Help Desk | B8: =SUMIFS(Payroll!$I:$I,Payroll!$D:$D,$F$1,Payroll!$H:$H,"IP",Payroll!$F:$F,"P2P*",Payroll!$K:$K,$A8) -> 1 | F8: =+B8+C8-D8-E8 -> 1 | G8: =+B8 -> 1 | H8: =+G8-F8 -> 0 | I8: =IF(N(G8)=0,"",IF(ABS(H8)<=0.02,"OK","Review")) -> OK
A9: Banking | B9: =SUMIFS(Payroll!$I:$I,Payroll!$D:$D,$F$1,Payroll!$H:$H,"IP",Payroll!$F:$F,"P2P*",Payroll!$K:$K,$A9) -> 3 | F9: =+B9+C9-D9-E9 -> 3 | G9: =+B9 -> 3 | H9: =+G9-F9 -> 0 | I9: =IF(N(G9)=0,"",IF(ABS(H9)<=0.02,"OK","Review")) -> OK
A11: AR | B11: =SUM(B12:B16) -> 18.675 | F11: =+B11+C11-D11-E11 -> 18.675 | G11: =+B11 -> 18.675 | H11: =+G11-F11 -> 0 | I11: =IF(N(G11)=0,"",IF(ABS(H11)<=0.02,"OK","Review")) -> OK
A12: AR IB | B12: =SUMIFS(Payroll!$I:$I,Payroll!$D:$D,$F$1,Payroll!$H:$H,"IP",Payroll!$K:$K,$A12) -> 13.675 | F12: =+B12+C12-D12-E12 -> 13.675 | G12: =+B12 -> 13.675 | H12: =+G12-F12 -> 0 | I12: =IF(N(G12)=0,"",IF(ABS(H12)<=0.02,"OK","Review")) -> OK
A13: AR FR | B13: =SUMIFS(Payroll!$I:$I,Payroll!$D:$D,$F$1,Payroll!$H:$H,"IP",Payroll!$K:$K,$A13) -> 0 | F13: =+B13+C13-D13-E13 -> 0 | G13: =+B13 -> 0 | H13: =+G13-F13 -> 0 | I13: =IF(N(G13)=0,"",IF(ABS(H13)<=0.02,"OK","Review"))
A14: AR IT | B14: =SUMIFS(Payroll!$I:$I,Payroll!$D:$D,$F$1,Payroll!$H:$H,"IP",Payroll!$K:$K,$A14) -> 1 | F14: =+B14+C14-D14-E14 -> 1 | G14: =+B14 -> 1 | H14: =+G14-F14 -> 0 | I14: =IF(N(G14)=0,"",IF(ABS(H14)<=0.02,"OK","Review")) -> OK
A15: AR MA | B15: =SUMIFS(Payroll!$I:$I,Payroll!$D:$D,$F$1,Payroll!$H:$H,"IP",Payroll!$K:$K,$A15) -> 0 | F15: =+B15+C15-D15-E15 -> 0 | G15: =+B15 -> 0 | H15: =+G15-F15 -> 0 | I15: =IF(N(G15)=0,"",IF(ABS(H15)<=0.02,"OK","Review"))
A16: AR Banking | B16: =SUMIFS(Payroll!$I:$I,Payroll!$D:$D,$F$1,Payroll!$H:$H,"IP",Payroll!$K:$K,$A16) -> 4 | F16: =+B16+C16-D16-E16 -> 4 | G16: =+B16 -> 4 | H16: =+G16-F16 -> 0 | I16: =IF(N(G16)=0,"",IF(ABS(H16)<=0.02,"OK","Review")) -> OK
A18: R2R | B18: =SUM(B19:B23) -> 21 | F18: =+B18+C18-D18-E18 -> 21 | G18: =+B18 -> 21 | H18: =+G18-F18 -> 0 | I18: =IF(N(G18)=0,"",IF(ABS(H18)<=0.02,"OK","Review")) -> OK
A19: R2R IB | B19: =SUMIFS(Payroll!$I:$I,Payroll!$D:$D,$F$1,Payroll!$H:$H,"IP",Payroll!$K:$K,$A19) -> 19 | F19: =+B19+C19-D19-E19 -> 19 | G19: =+B19 -> 19 | H19: =+G19-F19 -> 0 | I19: =IF(N(G19)=0,"",IF(ABS(H19)<=0.02,"OK","Review")) -> OK
A20: R2R FR | B20: =SUMIFS(Payroll!$I:$I,Payroll!$D:$D,$F$1,Payroll!$H:$H,"IP",Payroll!$K:$K,$A20) -> 0 | F20: =+B20+C20-D20-E20 -> 0 | G20: =+B20 -> 0 | H20: =+G20-F20 -> 0 | I20: =IF(N(G20)=0,"",IF(ABS(H20)<=0.02,"OK","Review"))
A21: R2R IT | B21: =SUMIFS(Payroll!$I:$I,Payroll!$D:$D,$F$1,Payroll!$H:$H,"IP",Payroll!$K:$K,$A21) -> 0 | F21: =+B21+C21-D21-E21 -> 0 | G21: =+B21 -> 0 | H21: =+G21-F21 -> 0 | I21: =IF(N(G21)=0,"",IF(ABS(H21)<=0.02,"OK","Review"))
A22: R2R MA | B22: =SUMIFS(Payroll!$I:$I,Payroll!$D:$D,$F$1,Payroll!$H:$H,"IP",Payroll!$K:$K,$A22) -> 0 | F22: =+B22+C22-D22-E22 -> 0 | G22: =+B22 -> 0 | H22: =+G22-F22 -> 0 | I22: =IF(N(G22)=0,"",IF(ABS(H22)<=0.02,"OK","Review"))
A23: R2R Banking | B23: =SUMIFS(Payroll!$I:$I,Payroll!$D:$D,$F$1,Payroll!$H:$H,"IP",Payroll!$K:$K,$A23) -> 2 | F23: =+B23+C23-D23-E23 -> 2 | G23: =+B23 -> 2 | H23: =+G23-F23 -> 0 | I23: =IF(N(G23)=0,"",IF(ABS(H23)<=0.02,"OK","Review")) -> OK
A25: HR | B25: =SUMIFS(Payroll!$I:$I,Payroll!$D:$D,$F$1,Payroll!$H:$H,"IP",Payroll!$F:$F,"HR") -> 1 | F25: =+B25+C25-D25-E25 -> 1 | G25: =+B25 -> 1 | H25: =+G25-B25 -> 0 | I25: =IF(N(G25)=0,"",IF(ABS(H25)<=0.02,"OK","Review")) -> OK
A27: MD | B27: =SUMIFS(Payroll!$I:$I,Payroll!$D:$D,$F$1,Payroll!$H:$H,"IP",Payroll!$F:$F,"DM") -> 0 | F27: =+B27+C27-D27-E27 -> 0 | G27: =+B27 -> 0 | H27: =+G27-B27 -> 0 | I27: =IF(N(G27)=0,"",IF(ABS(H27)<=0.02,"OK","Review"))
A29: Subtotal (processes above) | B29: =B3+B11+B18+B25+B27 -> 64.475 | F29: =F3+F11+F18+F25+F27 -> 64.475 | G29: =G3+G11+G18+G25+G27 -> 64.475 | H29: =+G29-B29 -> 0 | I29: =IF(N(G29)=0,"",IF(ABS(H29)<=0.02,"OK","Review")) -> OK
A30: Out of scope (OoS) | B30: =SUMIFS(Payroll!$I:$I,Payroll!$D:$D,$F$1,Payroll!$H:$H,"IP",Payroll!$F:$F,"OoS") -> 0
A31: TOTAL PAYROLL (IP) | B31: =SUMIFS(Payroll!$I:$I,Payroll!$D:$D,$F$1,Payroll!$H:$H,"IP") -> 65.475
A32: Unexplained difference | B32: =B31-B29-B30 -> 1 | I32: =IF(ABS(B32)<=0.02,"OK","Review") -> Review
A34: ="Payroll "&$F$1&" · DSS "&TEXT(SUMIFS(Payroll!$I:$I,Payroll!$D:$D,$F$1,Payroll!$H:$H,"DSS"),"#,##0.00")&" + IP "&TEXT(SUMIFS(Payroll!$I:$I,Payroll!$D:$D,$F$1,Payroll!$H:$H,"IP"),"#,##0.00")&" + other business "&TEXT(SUMIFS(Payroll!$I:$I,Payroll!$D:$D,$F$1)-SUMIFS(Payroll!$I:$I,Payroll!$D:$D,$F$1,Payroll!$H:$H,"DSS")-SUMIFS(Payroll!$I:$I,Payroll!$D:$D,$F$1,Payroll!$H:$H,"IP"),"#,##0.00")&" = "&TEXT(SUMIFS(Payroll!$I:$I,Payroll!$D:$D,$F$1),"#,##0.00")&" · The IP Scorecard is not available yet: column F is a manual entry." -> Payroll AP09 · DSS 104,37500 + IP 65,47500 + other business 3,000 = 172,85000 · The IP Scorecard is not available yet: column F is a manual entry.

Sheet FTE Scorecard
A1: Definitions | B1: Scorecard Division | C1: Scorecard País | D1: Equipo | E1: Fecha | F1: FTE
A2: Total AP FTEs (all, incl. payments, team leaders, manager) | B2: DE_Pack | C2: DE | D2: DE | E2: 01/09/2026 | F2: 4.32
A3: Total AP FTEs (all, incl. payments, team leaders, manager) | B3: FR_Qualiac | C3: FR | D3: FR | E3: 01/09/2026 | F3: 9.03
A4: Total AP FTEs (all, incl. payments, team leaders, manager) | B4: IT_Paper | C4: IT | D4: IT | E4: 01/09/2026 | F4: 1.79
A5: Total AP FTEs (all, incl. payments, team leaders, manager) | B5: BE_Pack | C5: BE | D5: BE | E5: 01/09/2026 | F5: 2.01
A6: Total AP FTEs (all, incl. payments, team leaders, manager) | B6: NL_Pack | C6: BE | D6: BE | E6: 01/09/2026 | F6: 2.88
A7: Total AP FTEs (all, incl. payments, team leaders, manager) | B7: NL_PMS | C7: PMS | D7: PMS | E7: 01/09/2026 | F7: 1.75
A8: Total AP FTEs (all, incl. payments, team leaders, manager) | B8: UK_TMS | C8: TMS | D8: TMS | E8: 01/09/2026 | F8: 2
A9: Total AP FTEs (all, incl. payments, team leaders, manager) | B9: NL_Paper | C9: PS | D9: PS | E9: 01/09/2026 | F9: 4.5
A10: Total AP FTEs (all, incl. payments, team leaders, manager) | B10: UK_Pack | C10: UK | D10: UK | E10: 01/09/2026 | F10: 5.49
A11: Total AP FTEs (all, incl. payments, team leaders, manager) | B11: UK_Paper | C11: UK | D11: UK | E11: 01/09/2026 | F11: 1.88
A12: Total AP FTEs (all, incl. payments, team leaders, manager) | B12: UK_PLC | C12: UK | D12: UK | E12: 01/09/2026 | F12: 0.43
A13: Total AP FTEs (all, incl. payments, team leaders, manager) | B13: UK_Recycling | C13: UK | D13: UK | E13: 01/09/2026 | F13: 2.2
... A26: Total AP FTEs (all, incl. payments, team leaders, manager) | B26: Paper Iberia | C26: - | D26: IB | E26: 01/09/2026 | F26: 3.41006

Sheet Payroll
A1: Cost centre | B1: Employee no. | C1: Employee name | D1: Period | E1: Calendar year | F1: Process | G1: Sub-process | H1: Business | I1: FTE | J1: Team | K1: Category
A2: ES1101 | B2: PT1 | C2: Ines Martins | D2: AP09 | E2: 2026 | F2: Q2C | H2: DSS | I2: 1 | J2: Iberia | K2: =IF($D2="","",IFERROR(INDEX(Mapping!$H$3:$H$32,MATCH($B2,Mapping!$G$3:$G$32,0)),IF(LEFT($F2,3)="P2P",IFERROR(INDEX(Mapping!$E$3:$E$6,MATCH($G2,Mapping!$D$3:$D$6,0)),IFERROR(INDEX(Mapping!$B$3:$B$13,MATCH($J2,Mapping!$A$3:$A$13,0)),"(unmapped)")),IFERROR(INDEX(Mapping!$B$17:$B$22,MATCH($F2,Mapping!$A$17:$A$22,0)),$F2)&" "&IF($G2="Banking","Banking",IFERROR(INDEX(Mapping!$E$17:$E$28,MATCH($J2,Mapping!$D$17:$D$28,0)),"(unmapped)"))))) -> AR IB
A3: ES1101 | B3: PT2 | C3: Claudia Couto | D3: AP09 | E3: 2026 | F3: Q2C | H3: DSS | I3: 1 | J3: Iberia | K3: =IF($D3="","",IFERROR(INDEX(Mapping!$H$3:$H$32,MATCH($B3,Mapping!$G$3:$G$32,0)),IF(LEFT($F3,3)="P2P",IFERROR(INDEX(Mapping!$E$3:$E$6,MATCH($G3,Mapping!$D$3:$D$6,0)),IFERROR(INDEX(Mapping!$B$3:$B$13,MATCH($J3,Mapping!$A$3:$A$13,0)),"(unmapped)")),IFERROR(INDEX(Mapping!$B$17:$B$22,MATCH($F3,Mapping!$A$17:$A$22,0)),$F3)&" "&IF($G3="Banking","Banking",IFERROR(INDEX(Mapping!$E$17:$E$28,MATCH($J3,Mapping!$D$17:$D$28,0)),"(unmapped)"))))) -> AR IB
A4: 10000570 | B4: 100122 | C4: Yolanda Lazaro Esteban | D4: AP09 | E4: 2026 | F4: P2P | H4: DSS | I4: 1 | J4: Iberia | K4: =IF($D4="","",IFERROR(INDEX(Mapping!$H$3:$H$32,MATCH($B4,Mapping!$G$3:$G$32,0)),IF(LEFT($F4,3)="P2P",IFERROR(INDEX(Mapping!$E$3:$E$6,MATCH($G4,Mapping!$D$3:$D$6,0)),IFERROR(INDEX(Mapping!$B$3:$B$13,MATCH($J4,Mapping!$A$3:$A$13,0)),"(unmapped)")),IFERROR(INDEX(Mapping!$B$17:$B$22,MATCH($F4,Mapping!$A$17:$A$22,0)),$F4)&" "&IF($G4="Banking","Banking",IFERROR(INDEX(Mapping!$E$17:$E$28,MATCH($J4,Mapping!$D$17:$D$28,0)),"(unmapped)"))))) -> AP IB
A5: 10000570 | B5: 100282 | C5: BLANCO TIJERO, RITA | D5: AP09 | E5: 2026 | F5: P2P | H5: DSS | I5: 1 | J5: Iberia | K5: =IF($D5="","",IFERROR(INDEX(Mapping!$H$3:$H$32,MATCH($B5,Mapping!$G$3:$G$32,0)),IF(LEFT($F5,3)="P2P",IFERROR(INDEX(Mapping!$E$3:$E$6,MATCH($G5,Mapping!$D$3:$D$6,0)),IFERROR(INDEX(Mapping!$B$3:$B$13,MATCH($J5,Mapping!$A$3:$A$13,0)),"(unmapped)")),IFERROR(INDEX(Mapping!$B$17:$B$22,MATCH($F5,Mapping!$A$17:$A$22,0)),$F5)&" "&IF($G5="Banking","Banking",IFERROR(INDEX(Mapping!$E$17:$E$28,MATCH($J5,Mapping!$D$17:$D$28,0)),"(unmapped)"))))) -> AP IB
A6: 10000570 | B6: 100386 | C6: RODRIGUEZ VAZQUEZ, TERESA | D6: AP09 | E6: 2026 | F6: Q2C | H6: DSS | I6: 1 | J6: Iberia | K6: =IF($D6="","",IFERROR(INDEX(Mapping!$H$3:$H$32,MATCH($B6,Mapping!$G$3:$G$32,0)),IF(LEFT($F6,3)="P2P",IFERROR(INDEX(Mapping!$E$3:$E$6,MATCH($G6,Mapping!$D$3:$D$6,0)),IFERROR(INDEX(Mapping!$B$3:$B$13,MATCH($J6,Mapping!$A$3:$A$13,0)),"(unmapped)")),IFERROR(INDEX(Mapping!$B$17:$B$22,MATCH($F6,Mapping!$A$17:$A$22,0)),$F6)&" "&IF($G6="Banking","Banking",IFERROR(INDEX(Mapping!$E$17:$E$28,MATCH($J6,Mapping!$D$17:$D$28,0)),"(unmapped)"))))) -> AR IB
A7: 10000570 | B7: 100487 | C7: ALFONSO DEL VALLE, ALICIA | D7: AP09 | E7: 2026 | F7: P2P Vuelta | H7: DSS | I7: 1 | J7: FR | K7: =IF($D7="","",IFERROR(INDEX(Mapping!$H$3:$H$32,MATCH($B7,Mapping!$G$3:$G$32,0)),IF(LEFT($F7,3)="P2P",IFERROR(INDEX(Mapping!$E$3:$E$6,MATCH($G7,Mapping!$D$3:$D$6,0)),IFERROR(INDEX(Mapping!$B$3:$B$13,MATCH($J7,Mapping!$A$3:$A$13,0)),"(unmapped)")),IFERROR(INDEX(Mapping!$B$17:$B$22,MATCH($F7,Mapping!$A$17:$A$22,0)),$F7)&" "&IF($G7="Banking","Banking",IFERROR(INDEX(Mapping!$E$17:$E$28,MATCH($J7,Mapping!$D$17:$D$28,0)),"(unmapped)"))))) -> P2P Vuelta FR
A8: 10000570 | B8: 100511 | C8: INGELMO GOMEZ MARCOS | D8: AP09 | E8: 2026 | F8: Q2C | H8: DSS | I8: 1 | J8: Iberia | K8: =IF($D8="","",IFERROR(INDEX(Mapping!$H$3:$H$32,MATCH($B8,Mapping!$G$3:$G$32,0)),IF(LEFT($F8,3)="P2P",IFERROR(INDEX(Mapping!$E$3:$E$6,MATCH($G8,Mapping!$D$3:$D$6,0)),IFERROR(INDEX(Mapping!$B$3:$B$13,MATCH($J8,Mapping!$A$3:$A$13,0)),"(unmapped)")),IFERROR(INDEX(Mapping!$B$17:$B$22,MATCH($F8,Mapping!$A$17:$A$22,0)),$F8)&" "&IF($G8="Banking","Banking",IFERROR(INDEX(Mapping!$E$17:$E$28,MATCH($J8,Mapping!$D$17:$D$28,0)),"(unmapped)"))))) -> AR IB
A9: 10000570 | B9: 100839 | C9: CALLEJA GUERRA, JULIO JOSE | D9: AP09 | E9: 2026 | F9: R2R | G9: Banking | H9: IP | I9: 1 | J9: Iberia | K9: =IF($D9="","",IFERROR(INDEX(Mapping!$H$3:$H$32,MATCH($B9,Mapping!$G$3:$G$32,0)),IF(LEFT($F9,3)="P2P",IFERROR(INDEX(Mapping!$E$3:$E$6,MATCH($G9,Mapping!$D$3:$D$6,0)),IFERROR(INDEX(Mapping!$B$3:$B$13,MATCH($J9,Mapping!$A$3:$A$13,0)),"(unmapped)")),IFERROR(INDEX(Mapping!$B$17:$B$22,MATCH($F9,Mapping!$A$17:$A$22,0)),$F9)&" "&IF($G9="Banking","Banking",IFERROR(INDEX(Mapping!$E$17:$E$28,MATCH($J9,Mapping!$D$17:$D$28,0)),"(unmapped)"))))) -> R2R Banking
A10: 10000570 | B10: 100958 | C10: CAMARERO CARRION, CRISTINA | D10: AP09 | E10: 2026 | F10: R2R | H10: DSS | I10: 1 | J10: Kunheim | K10: =IF($D10="","",IFERROR(INDEX(Mapping!$H$3:$H$32,MATCH($B10,Mapping!$G$3:$G$32,0)),IF(LEFT($F10,3)="P2P",IFERROR(INDEX(Mapping!$E$3:$E$6,MATCH($G10,Mapping!$D$3:$D$6,0)),IFERROR(INDEX(Mapping!$B$3:$B$13,MATCH($J10,Mapping!$A$3:$A$13,0)),"(unmapped)")),IFERROR(INDEX(Mapping!$B$17:$B$22,MATCH($F10,Mapping!$A$17:$A$22,0)),$F10)&" "&IF($G10="Banking","Banking",IFERROR(INDEX(Mapping!$E$17:$E$28,MATCH($J10,Mapping!$D$17:$D$28,0)),"(unmapped)"))))) -> R2R Kunheim
A11: 10000570 | B11: 100980 | C11: DIEZ GONZALEZ, BELEN | D11: AP09 | E11: 2026 | F11: R2R | H11: DSS | I11: 0.875 | J11: Iberia | K11: =IF($D11="","",IFERROR(INDEX(Mapping!$H$3:$H$32,MATCH($B11,Mapping!$G$3:$G$32,0)),IF(LEFT($F11,3)="P2P",IFERROR(INDEX(Mapping!$E$3:$E$6,MATCH($G11,Mapping!$D$3:$D$6,0)),IFERROR(INDEX(Mapping!$B$3:$B$13,MATCH($J11,Mapping!$A$3:$A$13,0)),"(unmapped)")),IFERROR(INDEX(Mapping!$B$17:$B$22,MATCH($F11,Mapping!$A$17:$A$22,0)),$F11)&" "&IF($G11="Banking","Banking",IFERROR(INDEX(Mapping!$E$17:$E$28,MATCH($J11,Mapping!$D$17:$D$28,0)),"(unmapped)"))))) -> R2R IB
A12: 10000570 | B12: 101011 | C12: BUJIDOS CHACON, NEREA | D12: AP09 | E12: 2026 | F12: P2P | H12: IP | I12: 1 | J12: Iberia | K12: =IF($D12="","",IFERROR(INDEX(Mapping!$H$3:$H$32,MATCH($B12,Mapping!$G$3:$G$32,0)),IF(LEFT($F12,3)="P2P",IFERROR(INDEX(Mapping!$E$3:$E$6,MATCH($G12,Mapping!$D$3:$D$6,0)),IFERROR(INDEX(Mapping!$B$3:$B$13,MATCH($J12,Mapping!$A$3:$A$13,0)),"(unmapped)")),IFERROR(INDEX(Mapping!$B$17:$B$22,MATCH($F12,Mapping!$A$17:$A$22,0)),$F12)&" "&IF($G12="Banking","Banking",IFERROR(INDEX(Mapping!$E$17:$E$28,MATCH($J12,Mapping!$D$17:$D$28,0)),"(unmapped)"))))) -> AP IB
A13: 10000570 | B13: 101019 | C13: MERINO LOPEZ, VICTOR | D13: AP09 | E13: 2026 | F13: R2R | H13: IP | I13: 1 | J13: Iberia | K13: =IF($D13="","",IFERROR(INDEX(Mapping!$H$3:$H$32,MATCH($B13,Mapping!$G$3:$G$32,0)),IF(LEFT($F13,3)="P2P",IFERROR(INDEX(Mapping!$E$3:$E$6,MATCH($G13,Mapping!$D$3:$D$6,0)),IFERROR(INDEX(Mapping!$B$3:$B$13,MATCH($J13,Mapping!$A$3:$A$13,0)),"(unmapped)")),IFERROR(INDEX(Mapping!$B$17:$B$22,MATCH($F13,Mapping!$A$17:$A$22,0)),$F13)&" "&IF($G13="Banking","Banking",IFERROR(INDEX(Mapping!$E$17:$E$28,MATCH($J13,Mapping!$D$17:$D$28,0)),"(unmapped)"))))) -> R2R IB
A14: 10000570 | B14: 101034 | C14: SULLIVAN, EVE KATHLEEN | D14: AP09 | E14: 2026 | F14: P2P | H14: DSS | I14: 1 | J14: General | K14: =IF($D14="","",IFERROR(INDEX(Mapping!$H$3:$H$32,MATCH($B14,Mapping!$G$3:$G$32,0)),IF(LEFT($F14,3)="P2P",IFERROR(INDEX(Mapping!$E$3:$E$6,MATCH($G14,Mapping!$D$3:$D$6,0)),IFERROR(INDEX(Mapping!$B$3:$B$13,MATCH($J14,Mapping!$A$3:$A$13,0)),"(unmapped)")),IFERROR(INDEX(Mapping!$B$17:$B$22,MATCH($F14,Mapping!$A$17:$A$22,0)),$F14)&" "&IF($G14="Banking","Banking",IFERROR(INDEX(Mapping!$E$17:$E$28,MATCH($J14,Mapping!$D$17:$D$28,0)),"(unmapped)"))))) -> AP General
A15: 10000570 | B15: 101036 | C15: PRIETO ROJO, MARIA NATALIA | D15: AP09 | E15: 2026 | F15: P2P | G15: Helpdesk | H15: IP | I15: 1 | J15: Iberia | K15: =IF($D15="","",IFERROR(INDEX(Mapping!$H$3:$H$32,MATCH($B15,Mapping!$G$3:$G$32,0)),IF(LEFT($F15,3)="P2P",IFERROR(INDEX(Mapping!$E$3:$E$6,MATCH($G15,Mapping!$D$3:$D$6,0)),IFERROR(INDEX(Mapping!$B$3:$B$13,MATCH($J15,Mapping!$A$3:$A$13,0)),"(unmapped)")),IFERROR(INDEX(Mapping!$B$17:$B$22,MATCH($F15,Mapping!$A$17:$A$22,0)),$F15)&" "&IF($G15="Banking","Banking",IFERROR(INDEX(Mapping!$E$17:$E$28,MATCH($J15,Mapping!$D$17:$D$28,0)),"(unmapped)"))))) -> AP Help Desk
A16: 10000570 | B16: 101047 | C16: ESCAÑO CASTAÑO, LAURA | D16: AP09 | E16: 2026 | F16: P2P | H16: DSS | I16: 1 | J16: Iberia | K16: =IF($D16="","",IFERROR(INDEX(Mapping!$H$3:$H$32,MATCH($B16,Mapping!$G$3:$G$32,0)),IF(LEFT($F16,3)="P2P",IFERROR(INDEX(Mapping!$E$3:$E$6,MATCH($G16,Mapping!$D$3:$D$6,0)),IFERROR(INDEX(Mapping!$B$3:$B$13,MATCH($J16,Mapping!$A$3:$A$13,0)),"(unmapped)")),IFERROR(INDEX(Mapping!$B$17:$B$22,MATCH($F16,Mapping!$A$17:$A$22,0)),$F16)&" "&IF($G16="Banking","Banking",IFERROR(INDEX(Mapping!$E$17:$E$28,MATCH($J16,Mapping!$D$17:$D$28,0)),"(unmapped)"))))) -> AP IB
A17: 10000570 | B17: 101048 | C17: VARELA RICO, CRISTINA | D17: AP09 | E17: 2026 | F17: R2R | H17: DSS | I17: 1 | J17: Iberia | K17: =IF($D17="","",IFERROR(INDEX(Mapping!$H$3:$H$32,MATCH($B17,Mapping!$G$3:$G$32,0)),IF(LEFT($F17,3)="P2P",IFERROR(INDEX(Mapping!$E$3:$E$6,MATCH($G17,Mapping!$D$3:$D$6,0)),IFERROR(INDEX(Mapping!$B$3:$B$13,MATCH($J17,Mapping!$A$3:$A$13,0)),"(unmapped)")),IFERROR(INDEX(Mapping!$B$17:$B$22,MATCH($F17,Mapping!$A$17:$A$22,0)),$F17)&" "&IF($G17="Banking","Banking",IFERROR(INDEX(Mapping!$E$17:$E$28,MATCH($J17,Mapping!$D$17:$D$28,0)),"(unmapped)"))))) -> R2R IB
A18: 10000570 | B18: 101307 | C18: TORRES BARRIENTOS, OLGA PATRICIA | D18: AP09 | E18: 2026 | F18: R2R | H18: DSS | I18: 0.875 | J18: Iberia | K18: =IF($D18="","",IFERROR(INDEX(Mapping!$H$3:$H$32,MATCH($B18,Mapping!$G$3:$G$32,0)),IF(LEFT($F18,3)="P2P",IFERROR(INDEX(Mapping!$E$3:$E$6,MATCH($G18,Mapping!$D$3:$D$6,0)),IFERROR(INDEX(Mapping!$B$3:$B$13,MATCH($J18,Mapping!$A$3:$A$13,0)),"(unmapped)")),IFERROR(INDEX(Mapping!$B$17:$B$22,MATCH($F18,Mapping!$A$17:$A$22,0)),$F18)&" "&IF($G18="Banking","Banking",IFERROR(INDEX(Mapping!$E$17:$E$28,MATCH($J18,Mapping!$D$17:$D$28,0)),"(unmapped)"))))) -> R2R IB
A19: ES1101 | B19: 101193 | C19: ANGELA ESCOBAR BARBOSA | D19: AP09 | E19: 2026 | F19: P2P | H19: DSS | I19: 1 | J19: Mejora | K19: =IF($D19="","",IFERROR(INDEX(Mapping!$H$3:$H$32,MATCH($B19,Mapping!$G$3:$G$32,0)),IF(LEFT($F19,3)="P2P",IFERROR(INDEX(Mapping!$E$3:$E$6,MATCH($G19,Mapping!$D$3:$D$6,0)),IFERROR(INDEX(Mapping!$B$3:$B$13,MATCH($J19,Mapping!$A$3:$A$13,0)),"(unmapped)")),IFERROR(INDEX(Mapping!$B$17:$B$22,MATCH($F19,Mapping!$A$17:$A$22,0)),$F19)&" "&IF($G19="Banking","Banking",IFERROR(INDEX(Mapping!$E$17:$E$28,MATCH($J19,Mapping!$D$17:$D$28,0)),"(unmapped)"))))) -> AP Continuos improvement
A20: ES1101 | B20: 101409 | C20: BRUNO TIAGO FERRO MARTINS | D20: AP09 | E20: 2026 | F20: DM | H20: DSS | I20: 1 | J20: Iberia | K20: =IF($D20="","",IFERROR(INDEX(Mapping!$H$3:$H$32,MATCH($B20,Mapping!$G$3:$G$32,0)),IF(LEFT($F20,3)="P2P",IFERROR(INDEX(Mapping!$E$3:$E$6,MATCH($G20,Mapping!$D$3:$D$6,0)),IFERROR(INDEX(Mapping!$B$3:$B$13,MATCH($J20,Mapping!$A$3:$A$13,0)),"(unmapped)")),IFERROR(INDEX(Mapping!$B$17:$B$22,MATCH($F20,Mapping!$A$17:$A$22,0)),$F20)&" "&IF($G20="Banking","Banking",IFERROR(INDEX(Mapping!$E$17:$E$28,MATCH($J20,Mapping!$D$17:$D$28,0)),"(unmapped)"))))) -> MD IB
A21: ES1101 | B21: 101414 | C21: ZOILO GIL PEREZ | D21: AP09 | E21: 2026 | F21: Q2C | H21: DSS | I21: 1 | J21: Iberia | K21: =IF($D21="","",IFERROR(INDEX(Mapping!$H$3:$H$32,MATCH($B21,Mapping!$G$3:$G$32,0)),IF(LEFT($F21,3)="P2P",IFERROR(INDEX(Mapping!$E$3:$E$6,MATCH($G21,Mapping!$D$3:$D$6,0)),IFERROR(INDEX(Mapping!$B$3:$B$13,MATCH($J21,Mapping!$A$3:$A$13,0)),"(unmapped)")),IFERROR(INDEX(Mapping!$B$17:$B$22,MATCH($F21,Mapping!$A$17:$A$22,0)),$F21)&" "&IF($G21="Banking","Banking",IFERROR(INDEX(Mapping!$E$17:$E$28,MATCH($J21,Mapping!$D$17:$D$28,0)),"(unmapped)"))))) -> AR IB
A22: ES1101 | B22: 101417 | C22: FRANCISCO JOSE MANZANILLA MULLOR | D22: AP09 | E22: 2026 | F22: R2R | G22: Banking | H22: DSS | I22: 1 | J22: Iberia | K22: =IF($D22="","",IFERROR(INDEX(Mapping!$H$3:$H$32,MATCH($B22,Mapping!$G$3:$G$32,0)),IF(LEFT($F22,3)="P2P",IFERROR(INDEX(Mapping!$E$3:$E$6,MATCH($G22,Mapping!$D$3:$D$6,0)),IFERROR(INDEX(Mapping!$B$3:$B$13,MATCH($J22,Mapping!$A$3:$A$13,0)),"(unmapped)")),IFERROR(INDEX(Mapping!$B$17:$B$22,MATCH($F22,Mapping!$A$17:$A$22,0)),$F22)&" "&IF($G22="Banking","Banking",IFERROR(INDEX(Mapping!$E$17:$E$28,MATCH($J22,Mapping!$D$17:$D$28,0)),"(unmapped)"))))) -> R2R Banking
A23: ES1101 | B23: 101425 | C23: MARÍA DEL CARMEN CONDE SAN JOSÉ | D23: AP09 | E23: 2026 | F23: Q2C | H23: DSS | I23: 1 | J23: Iberia | K23: =IF($D23="","",IFERROR(INDEX(Mapping!$H$3:$H$32,MATCH($B23,Mapping!$G$3:$G$32,0)),IF(LEFT($F23,3)="P2P",IFERROR(INDEX(Mapping!$E$3:$E$6,MATCH($G23,Mapping!$D$3:$D$6,0)),IFERROR(INDEX(Mapping!$B$3:$B$13,MATCH($J23,Mapping!$A$3:$A$13,0)),"(unmapped)")),IFERROR(INDEX(Mapping!$B$17:$B$22,MATCH($F23,Mapping!$A$17:$A$22,0)),$F23)&" "&IF($G23="Banking","Banking",IFERROR(INDEX(Mapping!$E$17:$E$28,MATCH($J23,Mapping!$D$17:$D$28,0)),"(unmapped)"))))) -> AR IB
A24: ES1101 | B24: 101426 | C24: RAÚL VIÑAS ZAMORA | D24: AP09 | E24: 2026 | F24: P2P | H24: DSS | I24: 1 | J24: Iberia | K24: =IF($D24="","",IFERROR(INDEX(Mapping!$H$3:$H$32,MATCH($B24,Mapping!$G$3:$G$32,0)),IF(LEFT($F24,3)="P2P",IFERROR(INDEX(Mapping!$E$3:$E$6,MATCH($G24,Mapping!$D$3:$D$6,0)),IFERROR(INDEX(Mapping!$B$3:$B$13,MATCH($J24,Mapping!$A$3:$A$13,0)),"(unmapped)")),IFERROR(INDEX(Mapping!$B$17:$B$22,MATCH($F24,Mapping!$A$17:$A$22,0)),$F24)&" "&IF($G24="Banking","Banking",IFERROR(INDEX(Mapping!$E$17:$E$28,MATCH($J24,Mapping!$D$17:$D$28,0)),"(unmapped)"))))) -> AP IB
A25: ES1101 | B25: 101429 | C25: MARIA EVA ALVARO REDONDO | D25: AP09 | E25: 2026 | F25: Q2C | G25: Banking | H25: DSS | I25: 1 | J25: Iberia | K25: =IF($D25="","",IFERROR(INDEX(Mapping!$H$3:$H$32,MATCH($B25,Mapping!$G$3:$G$32,0)),IF(LEFT($F25,3)="P2P",IFERROR(INDEX(Mapping!$E$3:$E$6,MATCH($G25,Mapping!$D$3:$D$6,0)),IFERROR(INDEX(Mapping!$B$3:$B$13,MATCH($J25,Mapping!$A$3:$A$13,0)),"(unmapped)")),IFERROR(INDEX(Mapping!$B$17:$B$22,MATCH($F25,Mapping!$A$17:$A$22,0)),$F25)&" "&IF($G25="Banking","Banking",IFERROR(INDEX(Mapping!$E$17:$E$28,MATCH($J25,Mapping!$D$17:$D$28,0)),"(unmapped)"))))) -> AR Banking
A26: ES1101 | B26: 101430 | C26: ALBA FERNÁNDEZ LÓPEZ | D26: AP09 | E26: 2026 | F26: P2P Vuelta | H26: DSS | I26: 1 | J26: NL | K26: =IF($D26="","",IFERROR(INDEX(Mapping!$H$3:$H$32,MATCH($B26,Mapping!$G$3:$G$32,0)),IF(LEFT($F26,3)="P2P",IFERROR(INDEX(Mapping!$E$3:$E$6,MATCH($G26,Mapping!$D$3:$D$6,0)),IFERROR(INDEX(Mapping!$B$3:$B$13,MATCH($J26,Mapping!$A$3:$A$13,0)),"(unmapped)")),IFERROR(INDEX(Mapping!$B$17:$B$22,MATCH($F26,Mapping!$A$17:$A$22,0)),$F26)&" "&IF($G26="Banking","Banking",IFERROR(INDEX(Mapping!$E$17:$E$28,MATCH($J26,Mapping!$D$17:$D$28,0)),"(unmapped)"))))) -> P2P Vuelta BE
A27: ES1101 | B27: 101434 | C27: ALFONSO BARRIOS RABAZAS | D27: AP09 | E27: 2026 | F27: DM | H27: DSS | I27: 1 | J27: Iberia | K27: =IF($D27="","",IFERROR(INDEX(Mapping!$H$3:$H$32,MATCH($B27,Mapping!$G$3:$G$32,0)),IF(LEFT($F27,3)="P2P",IFERROR(INDEX(Mapping!$E$3:$E$6,MATCH($G27,Mapping!$D$3:$D$6,0)),IFERROR(INDEX(Mapping!$B$3:$B$13,MATCH($J27,Mapping!$A$3:$A$13,0)),"(unmapped)")),IFERROR(INDEX(Mapping!$B$17:$B$22,MATCH($F27,Mapping!$A$17:$A$22,0)),$F27)&" "&IF($G27="Banking","Banking",IFERROR(INDEX(Mapping!$E$17:$E$28,MATCH($J27,Mapping!$D$17:$D$28,0)),"(unmapped)"))))) -> MD IB
A28: ES1101 | B28: 101436 | C28: ISABEL DAMASO | D28: AP09 | E28: 2026 | F28: P2P Vuelta | G28: Helpdesk | H28: DSS | I28: 1 | J28: UK | K28: =IF($D28="","",IFERROR(INDEX(Mapping!$H$3:$H$32,MATCH($B28,Mapping!$G$3:$G$32,0)),IF(LEFT($F28,3)="P2P",IFERROR(INDEX(Mapping!$E$3:$E$6,MATCH($G28,Mapping!$D$3:$D$6,0)),IFERROR(INDEX(Mapping!$B$3:$B$13,MATCH($J28,Mapping!$A$3:$A$13,0)),"(unmapped)")),IFERROR(INDEX(Mapping!$B$17:$B$22,MATCH($F28,Mapping!$A$17:$A$22,0)),$F28)&" "&IF($G28="Banking","Banking",IFERROR(INDEX(Mapping!$E$17:$E$28,MATCH($J28,Mapping!$D$17:$D$28,0)),"(unmapped)"))))) -> P2P Vuelta UK
A29: ES1101 | B29: 101437 | C29: IRIS LÓPEZ ALMARAZ | D29: AP09 | E29: 2026 | F29: P2P Vuelta | H29: DSS | I29: 1 | J29: DE | K29: =IF($D29="","",IFERROR(INDEX(Mapping!$H$3:$H$32,MATCH($B29,Mapping!$G$3:$G$32,0)),IF(LEFT($F29,3)="P2P",IFERROR(INDEX(Mapping!$E$3:$E$6,MATCH($G29,Mapping!$D$3:$D$6,0)),IFERROR(INDEX(Mapping!$B$3:$B$13,MATCH($J29,Mapping!$A$3:$A$13,0)),"(unmapped)")),IFERROR(INDEX(Mapping!$B$17:$B$22,MATCH($F29,Mapping!$A$17:$A$22,0)),$F29)&" "&IF($G29="Banking","Banking",IFERROR(INDEX(Mapping!$E$17:$E$28,MATCH($J29,Mapping!$D$17:$D$28,0)),"(unmapped)"))))) -> P2P Vuelta DE
A30: ES1101 | B30: 101438 | C30: ANA MARÍA NUÑEZ MAGRO | D30: AP09 | E30: 2026 | F30: R2R | H30: DSS | I30: 1 | J30: Iberia | K30: =IF($D30="","",IFERROR(INDEX(Mapping!$H$3:$H$32,MATCH($B30,Mapping!$G$3:$G$32,0)),IF(LEFT($F30,3)="P2P",IFERROR(INDEX(Mapping!$E$3:$E$6,MATCH($G30,Mapping!$D$3:$D$6,0)),IFERROR(INDEX(Mapping!$B$3:$B$13,MATCH($J30,Mapping!$A$3:$A$13,0)),"(unmapped)")),IFERROR(INDEX(Mapping!$B$17:$B$22,MATCH($F30,Mapping!$A$17:$A$22,0)),$F30)&" "&IF($G30="Banking","Banking",IFERROR(INDEX(Mapping!$E$17:$E$28,MATCH($J30,Mapping!$D$17:$D$28,0)),"(unmapped)"))))) -> R2R IB
A31: ES1101 | B31: 101442 | C31: PABLO LUIS MARTIN ARRIBAS | D31: AP09 | E31: 2026 | F31: R2R | H31: IP | I31: 1 | J31: Iberia | K31: =IF($D31="","",IFERROR(INDEX(Mapping!$H$3:$H$32,MATCH($B31,Mapping!$G$3:$G$32,0)),IF(LEFT($F31,3)="P2P",IFERROR(INDEX(Mapping!$E$3:$E$6,MATCH($G31,Mapping!$D$3:$D$6,0)),IFERROR(INDEX(Mapping!$B$3:$B$13,MATCH($J31,Mapping!$A$3:$A$13,0)),"(unmapped)")),IFERROR(INDEX(Mapping!$B$17:$B$22,MATCH($F31,Mapping!$A$17:$A$22,0)),$F31)&" "&IF($G31="Banking","Banking",IFERROR(INDEX(Mapping!$E$17:$E$28,MATCH($J31,Mapping!$D$17:$D$28,0)),"(unmapped)"))))) -> R2R IB
A32: ES1101 | B32: 101443 | C32: DANIEL MENDEZ SILVA | D32: AP09 | E32: 2026 | F32: R2R | G32: Banking | H32: DSS | I32: 1 | J32: Iberia | K32: =IF($D32="","",IFERROR(INDEX(Mapping!$H$3:$H$32,MATCH($B32,Mapping!$G$3:$G$32,0)),IF(LEFT($F32,3)="P2P",IFERROR(INDEX(Mapping!$E$3:$E$6,MATCH($G32,Mapping!$D$3:$D$6,0)),IFERROR(INDEX(Mapping!$B$3:$B$13,MATCH($J32,Mapping!$A$3:$A$13,0)),"(unmapped)")),IFERROR(INDEX(Mapping!$B$17:$B$22,MATCH($F32,Mapping!$A$17:$A$22,0)),$F32)&" "&IF($G32="Banking","Banking",IFERROR(INDEX(Mapping!$E$17:$E$28,MATCH($J32,Mapping!$D$17:$D$28,0)),"(unmapped)"))))) -> R2R Banking
A33: ES1101 | B33: 101448 | C33: MARCIA PRADO ARGIBAY | D33: AP09 | E33: 2026 | F33: Q2C | H33: DSS | I33: 1 | J33: Iberia | K33: =IF($D33="","",IFERROR(INDEX(Mapping!$H$3:$H$32,MATCH($B33,Mapping!$G$3:$G$32,0)),IF(LEFT($F33,3)="P2P",IFERROR(INDEX(Mapping!$E$3:$E$6,MATCH($G33,Mapping!$D$3:$D$6,0)),IFERROR(INDEX(Mapping!$B$3:$B$13,MATCH($J33,Mapping!$A$3:$A$13,0)),"(unmapped)")),IFERROR(INDEX(Mapping!$B$17:$B$22,MATCH($F33,Mapping!$A$17:$A$22,0)),$F33)&" "&IF($G33="Banking","Banking",IFERROR(INDEX(Mapping!$E$17:$E$28,MATCH($J33,Mapping!$D$17:$D$28,0)),"(unmapped)"))))) -> AR IB
A34: ES1101 | B34: 101451 | C34: RUT ALVAREZ DOMINGUEZ | D34: AP09 | E34: 2026 | F34: R2R | H34: DSS | I34: 1 | J34: Iberia | K34: =IF($D34="","",IFERROR(INDEX(Mapping!$H$3:$H$32,MATCH($B34,Mapping!$G$3:$G$32,0)),IF(LEFT($F34,3)="P2P",IFERROR(INDEX(Mapping!$E$3:$E$6,MATCH($G34,Mapping!$D$3:$D$6,0)),IFERROR(INDEX(Mapping!$B$3:$B$13,MATCH($J34,Mapping!$A$3:$A$13,0)),"(unmapped)")),IFERROR(INDEX(Mapping!$B$17:$B$22,MATCH($F34,Mapping!$A$17:$A$22,0)),$F34)&" "&IF($G34="Banking","Banking",IFERROR(INDEX(Mapping!$E$17:$E$28,MATCH($J34,Mapping!$D$17:$D$28,0)),"(unmapped)"))))) -> R2R IB
A35: ES1101 | B35: 101458 | C35: JENNIFER CAROLINA JUANEDA PALACIOS | D35: AP09 | E35: 2026 | F35: P2P Vuelta | H35: DSS | I35: 1 | J35: UK | K35: =IF($D35="","",IFERROR(INDEX(Mapping!$H$3:$H$32,MATCH($B35,Mapping!$G$3:$G$32,0)),IF(LEFT($F35,3)="P2P",IFERROR(INDEX(Mapping!$E$3:$E$6,MATCH($G35,Mapping!$D$3:$D$6,0)),IFERROR(INDEX(Mapping!$B$3:$B$13,MATCH($J35,Mapping!$A$3:$A$13,0)),"(unmapped)")),IFERROR(INDEX(Mapping!$B$17:$B$22,MATCH($F35,Mapping!$A$17:$A$22,0)),$F35)&" "&IF($G35="Banking","Banking",IFERROR(INDEX(Mapping!$E$17:$E$28,MATCH($J35,Mapping!$D$17:$D$28,0)),"(unmapped)"))))) -> P2P Vuelta UK
A36: ES1101 | B36: 101460 | C36: NESTOR NIETO RAPOSO | D36: AP09 | E36: 2026 | F36: R2R | H36: DSS | I36: 0.875 | J36: Iberia | K36: =IF($D36="","",IFERROR(INDEX(Mapping!$H$3:$H$32,MATCH($B36,Mapping!$G$3:$G$32,0)),IF(LEFT($F36,3)="P2P",IFERROR(INDEX(Mapping!$E$3:$E$6,MATCH($G36,Mapping!$D$3:$D$6,0)),IFERROR(INDEX(Mapping!$B$3:$B$13,MATCH($J36,Mapping!$A$3:$A$13,0)),"(unmapped)")),IFERROR(INDEX(Mapping!$B$17:$B$22,MATCH($F36,Mapping!$A$17:$A$22,0)),$F36)&" "&IF($G36="Banking","Banking",IFERROR(INDEX(Mapping!$E$17:$E$28,MATCH($J36,Mapping!$D$17:$D$28,0)),"(unmapped)"))))) -> R2R IB
A37: ES1101 | B37: 102348 | C37: HECTOR CRESPO SOUSA | D37: AP09 | E37: 2026 | F37: P2P Vuelta | G37: Banking | H37: DSS | I37: 1 | J37: DE | K37: =IF($D37="","",IFERROR(INDEX(Mapping!$H$3:$H$32,MATCH($B37,Mapping!$G$3:$G$32,0)),IF(LEFT($F37,3)="P2P",IFERROR(INDEX(Mapping!$E$3:$E$6,MATCH($G37,Mapping!$D$3:$D$6,0)),IFERROR(INDEX(Mapping!$B$3:$B$13,MATCH($J37,Mapping!$A$3:$A$13,0)),"(unmapped)")),IFERROR(INDEX(Mapping!$B$17:$B$22,MATCH($F37,Mapping!$A$17:$A$22,0)),$F37)&" "&IF($G37="Banking","Banking",IFERROR(INDEX(Mapping!$E$17:$E$28,MATCH($J37,Mapping!$D$17:$D$28,0)),"(unmapped)"))))) -> P2P Vuelta Banking
A38: ES1101 | B38: 102349 | C38: ELENA CARRASCAL CANO | D38: AP09 | E38: 2026 | F38: P2P Vuelta | H38: DSS | I38: 1 | J38: Benelux | K38: =IF($D38="","",IFERROR(INDEX(Mapping!$H$3:$H$32,MATCH($B38,Mapping!$G$3:$G$32,0)),IF(LEFT($F38,3)="P2P",IFERROR(INDEX(Mapping!$E$3:$E$6,MATCH($G38,Mapping!$D$3:$D$6,0)),IFERROR(INDEX(Mapping!$B$3:$B$13,MATCH($J38,Mapping!$A$3:$A$13,0)),"(unmapped)")),IFERROR(INDEX(Mapping!$B$17:$B$22,MATCH($F38,Mapping!$A$17:$A$22,0)),$F38)&" "&IF($G38="Banking","Banking",IFERROR(INDEX(Mapping!$E$17:$E$28,MATCH($J38,Mapping!$D$17:$D$28,0)),"(unmapped)"))))) -> P2P Vuelta BE
A39: ES1101 | B39: 102394 | C39: RUTH TEREFE GEBREYES | D39: AP09 | E39: 2026 | F39: P2P Vuelta | G39: Helpdesk | H39: DSS | I39: 1 | J39: NL | K39: =IF($D39="","",IFERROR(INDEX(Mapping!$H$3:$H$32,MATCH($B39,Mapping!$G$3:$G$32,0)),IF(LEFT($F39,3)="P2P",IFERROR(INDEX(Mapping!$E$3:$E$6,MATCH($G39,Mapping!$D$3:$D$6,0)),IFERROR(INDEX(Mapping!$B$3:$B$13,MATCH($J39,Mapping!$A$3:$A$13,0)),"(unmapped)")),IFERROR(INDEX(Mapping!$B$17:$B$22,MATCH($F39,Mapping!$A$17:$A$22,0)),$F39)&" "&IF($G39="Banking","Banking",IFERROR(INDEX(Mapping!$E$17:$E$28,MATCH($J39,Mapping!$D$17:$D$28,0)),"(unmapped)"))))) -> P2P Vuelta BE
A40: ES1101 | B40: 102397 | C40: MARIA MARTINEZ SIMÓN | D40: AP09 | E40: 2026 | F40: R2R | H40: DSS | I40: 1 | J40: Iberia | K40: =IF($D40="","",IFERROR(INDEX(Mapping!$H$3:$H$32,MATCH($B40,Mapping!$G$3:$G$32,0)),IF(LEFT($F40,3)="P2P",IFERROR(INDEX(Mapping!$E$3:$E$6,MATCH($G40,Mapping!$D$3:$D$6,0)),IFERROR(INDEX(Mapping!$B$3:$B$13,MATCH($J40,Mapping!$A$3:$A$13,0)),"(unmapped)")),IFERROR(INDEX(Mapping!$B$17:$B$22,MATCH($F40,Mapping!$A$17:$A$22,0)),$F40)&" "&IF($G40="Banking","Banking",IFERROR(INDEX(Mapping!$E$17:$E$28,MATCH($J40,Mapping!$D$17:$D$28,0)),"(unmapped)"))))) -> R2R IB
A41: ES1101 | B41: 102435 | C41: MARÍA MOREDA RETORTILLO | D41: AP09 | E41: 2026 | F41: Q2C | H41: DSS | I41: 1 | J41: Iberia | K41: =IF($D41="","",IFERROR(INDEX(Mapping!$H$3:$H$32,MATCH($B41,Mapping!$G$3:$G$32,0)),IF(LEFT($F41,3)="P2P",IFERROR(INDEX(Mapping!$E$3:$E$6,MATCH($G41,Mapping!$D$3:$D$6,0)),IFERROR(INDEX(Mapping!$B$3:$B$13,MATCH($J41,Mapping!$A$3:$A$13,0)),"(unmapped)")),IFERROR(INDEX(Mapping!$B$17:$B$22,MATCH($F41,Mapping!$A$17:$A$22,0)),$F41)&" "&IF($G41="Banking","Banking",IFERROR(INDEX(Mapping!$E$17:$E$28,MATCH($J41,Mapping!$D$17:$D$28,0)),"(unmapped)"))))) -> AR IB
A42: ES1101 | B42: 102441 | C42: ALINE SANTIAGO GARCIA | D42: AP09 | E42: 2026 | F42: Q2C | H42: DSS | I42: 1 | J42: Iberia | K42: =IF($D42="","",IFERROR(INDEX(Mapping!$H$3:$H$32,MATCH($B42,Mapping!$G$3:$G$32,0)),IF(LEFT($F42,3)="P2P",IFERROR(INDEX(Mapping!$E$3:$E$6,MATCH($G42,Mapping!$D$3:$D$6,0)),IFERROR(INDEX(Mapping!$B$3:$B$13,MATCH($J42,Mapping!$A$3:$A$13,0)),"(unmapped)")),IFERROR(INDEX(Mapping!$B$17:$B$22,MATCH($F42,Mapping!$A$17:$A$22,0)),$F42)&" "&IF($G42="Banking","Banking",IFERROR(INDEX(Mapping!$E$17:$E$28,MATCH($J42,Mapping!$D$17:$D$28,0)),"(unmapped)"))))) -> AR IB
A43: ES1101 | B43: 102447 | C43: SERGIO ESCUDERO VERDUGO | D43: AP09 | E43: 2026 | F43: Q2C | H43: IP | I43: 1 | J43: Iberia | K43: =IF($D43="","",IFERROR(INDEX(Mapping!$H$3:$H$32,MATCH($B43,Mapping!$G$3:$G$32,0)),IF(LEFT($F43,3)="P2P",IFERROR(INDEX(Mapping!$E$3:$E$6,MATCH($G43,Mapping!$D$3:$D$6,0)),IFERROR(INDEX(Mapping!$B$3:$B$13,MATCH($J43,Mapping!$A$3:$A$13,0)),"(unmapped)")),IFERROR(INDEX(Mapping!$B$17:$B$22,MATCH($F43,Mapping!$A$17:$A$22,0)),$F43)&" "&IF($G43="Banking","Banking",IFERROR(INDEX(Mapping!$E$17:$E$28,MATCH($J43,Mapping!$D$17:$D$28,0)),"(unmapped)"))))) -> AR IB
A44: ES1101 | B44: 102451 | C44: EVA MARTIN SANGINÉS | D44: AP09 | E44: 2026 | F44: R2R | H44: DSS | I44: 1 | J44: Kunheim | K44: =IF($D44="","",IFERROR(INDEX(Mapping!$H$3:$H$32,MATCH($B44,Mapping!$G$3:$G$32,0)),IF(LEFT($F44,3)="P2P",IFERROR(INDEX(Mapping!$E$3:$E$6,MATCH($G44,Mapping!$D$3:$D$6,0)),IFERROR(INDEX(Mapping!$B$3:$B$13,MATCH($J44,Mapping!$A$3:$A$13,0)),"(unmapped)")),IFERROR(INDEX(Mapping!$B$17:$B$22,MATCH($F44,Mapping!$A$17:$A$22,0)),$F44)&" "&IF($G44="Banking","Banking",IFERROR(INDEX(Mapping!$E$17:$E$28,MATCH($J44,Mapping!$D$17:$D$28,0)),"(unmapped)"))))) -> R2R Kunheim
A45: ES1101 | B45: 102466 | C45: MUTLU SUHAT DOLAPCHIEV | D45: AP09 | E45: 2026 | F45: P2P Vuelta | H45: DSS | I45: 1 | J45: FR | K45: =IF($D45="","",IFERROR(INDEX(Mapping!$H$3:$H$32,MATCH($B45,Mapping!$G$3:$G$32,0)),IF(LEFT($F45,3)="P2P",IFERROR(INDEX(Mapping!$E$3:$E$6,MATCH($G45,Mapping!$D$3:$D$6,0)),IFERROR(INDEX(Mapping!$B$3:$B$13,MATCH($J45,Mapping!$A$3:$A$13,0)),"(unmapped)")),IFERROR(INDEX(Mapping!$B$17:$B$22,MATCH($F45,Mapping!$A$17:$A$22,0)),$F45)&" "&IF($G45="Banking","Banking",IFERROR(INDEX(Mapping!$E$17:$E$28,MATCH($J45,Mapping!$D$17:$D$28,0)),"(unmapped)"))))) -> P2P Vuelta FR
A46: ES1101 | B46: 102503 | C46: CRISTINA ORTEGA PICÓN | D46: AP09 | E46: 2026 | F46: Q2C | G46: Banking | H46: IP | I46: 1 | J46: Iberia | K46: =IF($D46="","",IFERROR(INDEX(Mapping!$H$3:$H$32,MATCH($B46,Mapping!$G$3:$G$32,0)),IF(LEFT($F46,3)="P2P",IFERROR(INDEX(Mapping!$E$3:$E$6,MATCH($G46,Mapping!$D$3:$D$6,0)),IFERROR(INDEX(Mapping!$B$3:$B$13,MATCH($J46,Mapping!$A$3:$A$13,0)),"(unmapped)")),IFERROR(INDEX(Mapping!$B$17:$B$22,MATCH($F46,Mapping!$A$17:$A$22,0)),$F46)&" "&IF($G46="Banking","Banking",IFERROR(INDEX(Mapping!$E$17:$E$28,MATCH($J46,Mapping!$D$17:$D$28,0)),"(unmapped)"))))) -> AR Banking
A47: ES1101 | B47: 102509 | C47: DIANA GARCIA MORATE | D47: AP09 | E47: 2026 | F47: P2P Vuelta | H47: DSS | I47: 1 | J47: FR | K47: =IF($D47="","",IFERROR(INDEX(Mapping!$H$3:$H$32,MATCH($B47,Mapping!$G$3:$G$32,0)),IF(LEFT($F47,3)="P2P",IFERROR(INDEX(Mapping!$E$3:$E$6,MATCH($G47,Mapping!$D$3:$D$6,0)),IFERROR(INDEX(Mapping!$B$3:$B$13,MATCH($J47,Mapping!$A$3:$A$13,0)),"(unmapped)")),IFERROR(INDEX(Mapping!$B$17:$B$22,MATCH($F47,Mapping!$A$17:$A$22,0)),$F47)&" "&IF($G47="Banking","Banking",IFERROR(INDEX(Mapping!$E$17:$E$28,MATCH($J47,Mapping!$D$17:$D$28,0)),"(unmapped)"))))) -> P2P Vuelta FR
A48: ES1101 | B48: 102512 | C48: SARA GARCIA MERINO | D48: AP09 | E48: 2026 | F48: P2P Vuelta | H48: DSS | I48: 0.625 | J48: PS | K48: =IF($D48="","",IFERROR(INDEX(Mapping!$H$3:$H$32,MATCH($B48,Mapping!$G$3:$G$32,0)),IF(LEFT($F48,3)="P2P",IFERROR(INDEX(Mapping!$E$3:$E$6,MATCH($G48,Mapping!$D$3:$D$6,0)),IFERROR(INDEX(Mapping!$B$3:$B$13,MATCH($J48,Mapping!$A$3:$A$13,0)),"(unmapped)")),IFERROR(INDEX(Mapping!$B$17:$B$22,MATCH($F48,Mapping!$A$17:$A$22,0)),$F48)&" "&IF($G48="Banking","Banking",IFERROR(INDEX(Mapping!$E$17:$E$28,MATCH($J48,Mapping!$D$17:$D$28,0)),"(unmapped)"))))) -> P2P Vuelta PS
A49: ES1101 | B49: 102542 | C49: DIEGO REVUELTA CABALLERO | D49: AP09 | E49: 2026 | F49: Q2C | H49: DSS | I49: 1 | J49: Iberia | K49: =IF($D49="","",IFERROR(INDEX(Mapping!$H$3:$H$32,MATCH($B49,Mapping!$G$3:$G$32,0)),IF(LEFT($F49,3)="P2P",IFERROR(INDEX(Mapping!$E$3:$E$6,MATCH($G49,Mapping!$D$3:$D$6,0)),IFERROR(INDEX(Mapping!$B$3:$B$13,MATCH($J49,Mapping!$A$3:$A$13,0)),"(unmapped)")),IFERROR(INDEX(Mapping!$B$17:$B$22,MATCH($F49,Mapping!$A$17:$A$22,0)),$F49)&" "&IF($G49="Banking","Banking",IFERROR(INDEX(Mapping!$E$17:$E$28,MATCH($J49,Mapping!$D$17:$D$28,0)),"(unmapped)"))))) -> AR IB
A50: ES1101 | B50: 102571 | C50: MARÍA DEL PILAR BLANCO ESCALONA | D50: AP09 | E50: 2026 | F50: R2R | H50: DSS | I50: 1 | J50: Iberia | K50: =IF($D50="","",IFERROR(INDEX(Mapping!$H$3:$H$32,MATCH($B50,Mapping!$G$3:$G$32,0)),IF(LEFT($F50,3)="P2P",IFERROR(INDEX(Mapping!$E$3:$E$6,MATCH($G50,Mapping!$D$3:$D$6,0)),IFERROR(INDEX(Mapping!$B$3:$B$13,MATCH($J50,Mapping!$A$3:$A$13,0)),"(unmapped)")),IFERROR(INDEX(Mapping!$B$17:$B$22,MATCH($F50,Mapping!$A$17:$A$22,0)),$F50)&" "&IF($G50="Banking","Banking",IFERROR(INDEX(Mapping!$E$17:$E$28,MATCH($J50,Mapping!$D$17:$D$28,0)),"(unmapped)"))))) -> R2R IB
A51: ES1101 | B51: 102572 | C51: ADRIAN LOPEZ ARIAS | D51: AP09 | E51: 2026 | F51: R2R | H51: IP | I51: 1 | J51: Iberia | K51: =IF($D51="","",IFERROR(INDEX(Mapping!$H$3:$H$32,MATCH($B51,Mapping!$G$3:$G$32,0)),IF(LEFT($F51,3)="P2P",IFERROR(INDEX(Mapping!$E$3:$E$6,MATCH($G51,Mapping!$D$3:$D$6,0)),IFERROR(INDEX(Mapping!$B$3:$B$13,MATCH($J51,Mapping!$A$3:$A$13,0)),"(unmapped)")),IFERROR(INDEX(Mapping!$B$17:$B$22,MATCH($F51,Mapping!$A$17:$A$22,0)),$F51)&" "&IF($G51="Banking","Banking",IFERROR(INDEX(Mapping!$E$17:$E$28,MATCH($J51,Mapping!$D$17:$D$28,0)),"(unmapped)"))))) -> R2R IB
A52: ES1101 | B52: 102588 | C52: PATRICIA GALLEGO FERNANDEZ | D52: AP09 | E52: 2026 | F52: P2P | H52: IP | I52: 1 | J52: MA | K52: =IF($D52="","",IFERROR(INDEX(Mapping!$H$3:$H$32,MATCH($B52,Mapping!$G$3:$G$32,0)),IF(LEFT($F52,3)="P2P",IFERROR(INDEX(Mapping!$E$3:$E$6,MATCH($G52,Mapping!$D$3:$D$6,0)),IFERROR(INDEX(Mapping!$B$3:$B$13,MATCH($J52,Mapping!$A$3:$A$13,0)),"(unmapped)")),IFERROR(INDEX(Mapping!$B$17:$B$22,MATCH($F52,Mapping!$A$17:$A$22,0)),$F52)&" "&IF($G52="Banking","Banking",IFERROR(INDEX(Mapping!$E$17:$E$28,MATCH($J52,Mapping!$D$17:$D$28,0)),"(unmapped)"))))) -> AP MA
A53: ES1101 | B53: 102623 | C53: Idoya de la Puente Alvarez | D53: AP09 | E53: 2026 | F53: P2P Vuelta | H53: DSS | I53: 1 | J53: FR | K53: =IF($D53="","",IFERROR(INDEX(Mapping!$H$3:$H$32,MATCH($B53,Mapping!$G$3:$G$32,0)),IF(LEFT($F53,3)="P2P",IFERROR(INDEX(Mapping!$E$3:$E$6,MATCH($G53,Mapping!$D$3:$D$6,0)),IFERROR(INDEX(Mapping!$B$3:$B$13,MATCH($J53,Mapping!$A$3:$A$13,0)),"(unmapped)")),IFERROR(INDEX(Mapping!$B$17:$B$22,MATCH($F53,Mapping!$A$17:$A$22,0)),$F53)&" "&IF($G53="Banking","Banking",IFERROR(INDEX(Mapping!$E$17:$E$28,MATCH($J53,Mapping!$D$17:$D$28,0)),"(unmapped)"))))) -> P2P Vuelta FR
A54: ES1101 | B54: 102631 | C54: EDUARDO ANGEL DAVIES CARVAJAL | D54: AP09 | E54: 2026 | F54: P2P Vuelta | H54: DSS | I54: 1 | J54: PS | K54: =IF($D54="","",IFERROR(INDEX(Mapping!$H$3:$H$32,MATCH($B54,Mapping!$G$3:$G$32,0)),IF(LEFT($F54,3)="P2P",IFERROR(INDEX(Mapping!$E$3:$E$6,MATCH($G54,Mapping!$D$3:$D$6,0)),IFERROR(INDEX(Mapping!$B$3:$B$13,MATCH($J54,Mapping!$A$3:$A$13,0)),"(unmapped)")),IFERROR(INDEX(Mapping!$B$17:$B$22,MATCH($F54,Mapping!$A$17:$A$22,0)),$F54)&" "&IF($G54="Banking","Banking",IFERROR(INDEX(Mapping!$E$17:$E$28,MATCH($J54,Mapping!$D$17:$D$28,0)),"(unmapped)"))))) -> P2P Vuelta PS
A55: ES1101 | B55: 102643 | C55: FRANCISCO VELAZQUEZ BLANCO | D55: AP09 | E55: 2026 | F55: P2P Vuelta | H55: DSS | I55: 1 | J55: PS | K55: =IF($D55="","",IFERROR(INDEX(Mapping!$H$3:$H$32,MATCH($B55,Mapping!$G$3:$G$32,0)),IF(LEFT($F55,3)="P2P",IFERROR(INDEX(Mapping!$E$3:$E$6,MATCH($G55,Mapping!$D$3:$D$6,0)),IFERROR(INDEX(Mapping!$B$3:$B$13,MATCH($J55,Mapping!$A$3:$A$13,0)),"(unmapped)")),IFERROR(INDEX(Mapping!$B$17:$B$22,MATCH($F55,Mapping!$A$17:$A$22,0)),$F55)&" "&IF($G55="Banking","Banking",IFERROR(INDEX(Mapping!$E$17:$E$28,MATCH($J55,Mapping!$D$17:$D$28,0)),"(unmapped)"))))) -> P2P Vuelta PS
A56: ES1101 | B56: 102644 | C56: MARIYA MAGDALENA STEFANOVA DELCHEVA | D56: AP09 | E56: 2026 | F56: R2R | H56: IP | I56: 1 | J56: Iberia | K56: =IF($D56="","",IFERROR(INDEX(Mapping!$H$3:$H$32,MATCH($B56,Mapping!$G$3:$G$32,0)),IF(LEFT($F56,3)="P2P",IFERROR(INDEX(Mapping!$E$3:$E$6,MATCH($G56,Mapping!$D$3:$D$6,0)),IFERROR(INDEX(Mapping!$B$3:$B$13,MATCH($J56,Mapping!$A$3:$A$13,0)),"(unmapped)")),IFERROR(INDEX(Mapping!$B$17:$B$22,MATCH($F56,Mapping!$A$17:$A$22,0)),$F56)&" "&IF($G56="Banking","Banking",IFERROR(INDEX(Mapping!$E$17:$E$28,MATCH($J56,Mapping!$D$17:$D$28,0)),"(unmapped)"))))) -> R2R IB
A57: ES1101 | B57: 102826 | C57: NACHER MARTIN, SALOME | D57: AP09 | E57: 2026 | F57: Q2C | H57: DSS | I57: 1 | J57: Iberia | K57: =IF($D57="","",IFERROR(INDEX(Mapping!$H$3:$H$32,MATCH($B57,Mapping!$G$3:$G$32,0)),IF(LEFT($F57,3)="P2P",IFERROR(INDEX(Mapping!$E$3:$E$6,MATCH($G57,Mapping!$D$3:$D$6,0)),IFERROR(INDEX(Mapping!$B$3:$B$13,MATCH($J57,Mapping!$A$3:$A$13,0)),"(unmapped)")),IFERROR(INDEX(Mapping!$B$17:$B$22,MATCH($F57,Mapping!$A$17:$A$22,0)),$F57)&" "&IF($G57="Banking","Banking",IFERROR(INDEX(Mapping!$E$17:$E$28,MATCH($J57,Mapping!$D$17:$D$28,0)),"(unmapped)"))))) -> AR IB
A58: ES1101 | B58: 102865 | C58: FLOREZ GEIJO, JESÚS ALBERTO | D58: AP09 | E58: 2026 | F58: P2P | H58: IP | I58: 1 | J58: MA | K58: =IF($D58="","",IFERROR(INDEX(Mapping!$H$3:$H$32,MATCH($B58,Mapping!$G$3:$G$32,0)),IF(LEFT($F58,3)="P2P",IFERROR(INDEX(Mapping!$E$3:$E$6,MATCH($G58,Mapping!$D$3:$D$6,0)),IFERROR(INDEX(Mapping!$B$3:$B$13,MATCH($J58,Mapping!$A$3:$A$13,0)),"(unmapped)")),IFERROR(INDEX(Mapping!$B$17:$B$22,MATCH($F58,Mapping!$A$17:$A$22,0)),$F58)&" "&IF($G58="Banking","Banking",IFERROR(INDEX(Mapping!$E$17:$E$28,MATCH($J58,Mapping!$D$17:$D$28,0)),"(unmapped)"))))) -> AP MA
A59: ES1101 | B59: 102868 | C59: DE LA FUENTE PEÑA, SILVIA | D59: AP09 | E59: 2026 | F59: P2P | G59: Banking | H59: DSS | I59: 1 | J59: Kunheim | K59: =IF($D59="","",IFERROR(INDEX(Mapping!$H$3:$H$32,MATCH($B59,Mapping!$G$3:$G$32,0)),IF(LEFT($F59,3)="P2P",IFERROR(INDEX(Mapping!$E$3:$E$6,MATCH($G59,Mapping!$D$3:$D$6,0)),IFERROR(INDEX(Mapping!$B$3:$B$13,MATCH($J59,Mapping!$A$3:$A$13,0)),"(unmapped)")),IFERROR(INDEX(Mapping!$B$17:$B$22,MATCH($F59,Mapping!$A$17:$A$22,0)),$F59)&" "&IF($G59="Banking","Banking",IFERROR(INDEX(Mapping!$E$17:$E$28,MATCH($J59,Mapping!$D$17:$D$28,0)),"(unmapped)"))))) -> Banking
A60: ES1101 | B60: 102896 | C60: CITORES GARCÍA, ALBA | D60: AP09 | E60: 2026 | F60: P2P Vuelta | H60: DSS | I60: 1 | J60: PS | K60: =IF($D60="","",IFERROR(INDEX(Mapping!$H$3:$H$32,MATCH($B60,Mapping!$G$3:$G$32,0)),IF(LEFT($F60,3)="P2P",IFERROR(INDEX(Mapping!$E$3:$E$6,MATCH($G60,Mapping!$D$3:$D$6,0)),IFERROR(INDEX(Mapping!$B$3:$B$13,MATCH($J60,Mapping!$A$3:$A$13,0)),"(unmapped)")),IFERROR(INDEX(Mapping!$B$17:$B$22,MATCH($F60,Mapping!$A$17:$A$22,0)),$F60)&" "&IF($G60="Banking","Banking",IFERROR(INDEX(Mapping!$E$17:$E$28,MATCH($J60,Mapping!$D$17:$D$28,0)),"(unmapped)"))))) -> P2P Vuelta PS
A61: ES1101 | B61: 102917 | C61: COSTILLA BLANCO, JULIO | D61: AP09 | E61: 2026 | F61: Q2C | H61: IP | I61: 1 | J61: Iberia | K61: =IF($D61="","",IFERROR(INDEX(Mapping!$H$3:$H$32,MATCH($B61,Mapping!$G$3:$G$32,0)),IF(LEFT($F61,3)="P2P",IFERROR(INDEX(Mapping!$E$3:$E$6,MATCH($G61,Mapping!$D$3:$D$6,0)),IFERROR(INDEX(Mapping!$B$3:$B$13,MATCH($J61,Mapping!$A$3:$A$13,0)),"(unmapped)")),IFERROR(INDEX(Mapping!$B$17:$B$22,MATCH($F61,Mapping!$A$17:$A$22,0)),$F61)&" "&IF($G61="Banking","Banking",IFERROR(INDEX(Mapping!$E$17:$E$28,MATCH($J61,Mapping!$D$17:$D$28,0)),"(unmapped)"))))) -> AR IB
A62: ES1101 | B62: 102918 | C62: RESCIGNO, LUCIANO PASCUAL | D62: AP09 | E62: 2026 | F62: Q2C | H62: DSS | I62: 1 | J62: Mejora | K62: =IF($D62="","",IFERROR(INDEX(Mapping!$H$3:$H$32,MATCH($B62,Mapping!$G$3:$G$32,0)),IF(LEFT($F62,3)="P2P",IFERROR(INDEX(Mapping!$E$3:$E$6,MATCH($G62,Mapping!$D$3:$D$6,0)),IFERROR(INDEX(Mapping!$B$3:$B$13,MATCH($J62,Mapping!$A$3:$A$13,0)),"(unmapped)")),IFERROR(INDEX(Mapping!$B$17:$B$22,MATCH($F62,Mapping!$A$17:$A$22,0)),$F62)&" "&IF($G62="Banking","Banking",IFERROR(INDEX(Mapping!$E$17:$E$28,MATCH($J62,Mapping!$D$17:$D$28,0)),"(unmapped)"))))) -> AR Improvement
A63: ES1101 | B63: 102933 | C63: MONGIL GONZALEZ, MARIA | D63: AP09 | E63: 2026 | F63: HR | H63: DSS | I63: 1 | J63: Iberia | K63: =IF($D63="","",IFERROR(INDEX(Mapping!$H$3:$H$32,MATCH($B63,Mapping!$G$3:$G$32,0)),IF(LEFT($F63,3)="P2P",IFERROR(INDEX(Mapping!$E$3:$E$6,MATCH($G63,Mapping!$D$3:$D$6,0)),IFERROR(INDEX(Mapping!$B$3:$B$13,MATCH($J63,Mapping!$A$3:$A$13,0)),"(unmapped)")),IFERROR(INDEX(Mapping!$B$17:$B$22,MATCH($F63,Mapping!$A$17:$A$22,0)),$F63)&" "&IF($G63="Banking","Banking",IFERROR(INDEX(Mapping!$E$17:$E$28,MATCH($J63,Mapping!$D$17:$D$28,0)),"(unmapped)"))))) -> HR IB
A64: ES1101 | B64: 102938 | C64: PEREZ VARELA, CELIA | D64: AP09 | E64: 2026 | F64: P2P Vuelta | G64: Helpdesk | H64: DSS | I64: 1 | J64: UK | K64: =IF($D64="","",IFERROR(INDEX(Mapping!$H$3:$H$32,MATCH($B64,Mapping!$G$3:$G$32,0)),IF(LEFT($F64,3)="P2P",IFERROR(INDEX(Mapping!$E$3:$E$6,MATCH($G64,Mapping!$D$3:$D$6,0)),IFERROR(INDEX(Mapping!$B$3:$B$13,MATCH($J64,Mapping!$A$3:$A$13,0)),"(unmapped)")),IFERROR(INDEX(Mapping!$B$17:$B$22,MATCH($F64,Mapping!$A$17:$A$22,0)),$F64)&" "&IF($G64="Banking","Banking",IFERROR(INDEX(Mapping!$E$17:$E$28,MATCH($J64,Mapping!$D$17:$D$28,0)),"(unmapped)"))))) -> P2P Vuelta UK
A65: ES1101 | B65: 102946 | C65: SAROBE EZPONDA, BEATRIZ MARTA | D65: AP09 | E65: 2026 | F65: R2R | H65: DSS | I65: 1 | J65: Kunheim | K65: =IF($D65="","",IFERROR(INDEX(Mapping!$H$3:$H$32,MATCH($B65,Mapping!$G$3:$G$32,0)),IF(LEFT($F65,3)="P2P",IFERROR(INDEX(Mapping!$E$3:$E$6,MATCH($G65,Mapping!$D$3:$D$6,0)),IFERROR(INDEX(Mapping!$B$3:$B$13,MATCH($J65,Mapping!$A$3:$A$13,0)),"(unmapped)")),IFERROR(INDEX(Mapping!$B$17:$B$22,MATCH($F65,Mapping!$A$17:$A$22,0)),$F65)&" "&IF($G65="Banking","Banking",IFERROR(INDEX(Mapping!$E$17:$E$28,MATCH($J65,Mapping!$D$17:$D$28,0)),"(unmapped)"))))) -> R2R Kunheim
A66: ES1101 | B66: 102976 | C66: SANZ ESTEBANEZ, SAMUEL | D66: AP09 | E66: 2026 | F66: P2P Vuelta | H66: DSS | I66: 1 | J66: UK | K66: =IF($D66="","",IFERROR(INDEX(Mapping!$H$3:$H$32,MATCH($B66,Mapping!$G$3:$G$32,0)),IF(LEFT($F66,3)="P2P",IFERROR(INDEX(Mapping!$E$3:$E$6,MATCH($G66,Mapping!$D$3:$D$6,0)),IFERROR(INDEX(Mapping!$B$3:$B$13,MATCH($J66,Mapping!$A$3:$A$13,0)),"(unmapped)")),IFERROR(INDEX(Mapping!$B$17:$B$22,MATCH($F66,Mapping!$A$17:$A$22,0)),$F66)&" "&IF($G66="Banking","Banking",IFERROR(INDEX(Mapping!$E$17:$E$28,MATCH($J66,Mapping!$D$17:$D$28,0)),"(unmapped)"))))) -> P2P Vuelta UK
A67: ES1101 | B67: 103000 | C67: MONTES LOPEZ, JORGE | D67: AP09 | E67: 2026 | F67: R2R | H67: DSS | I67: 1 | J67: Kunheim | K67: =IF($D67="","",IFERROR(INDEX(Mapping!$H$3:$H$32,MATCH($B67,Mapping!$G$3:$G$32,0)),IF(LEFT($F67,3)="P2P",IFERROR(INDEX(Mapping!$E$3:$E$6,MATCH($G67,Mapping!$D$3:$D$6,0)),IFERROR(INDEX(Mapping!$B$3:$B$13,MATCH($J67,Mapping!$A$3:$A$13,0)),"(unmapped)")),IFERROR(INDEX(Mapping!$B$17:$B$22,MATCH($F67,Mapping!$A$17:$A$22,0)),$F67)&" "&IF($G67="Banking","Banking",IFERROR(INDEX(Mapping!$E$17:$E$28,MATCH($J67,Mapping!$D$17:$D$28,0)),"(unmapped)"))))) -> R2R Kunheim
A68: ES1101 | B68: 103004 | C68: PEREZ MUCIENTES, JAVIER | D68: AP09 | E68: 2026 | F68: R2R | H68: IP | I68: 1 | J68: Iberia | K68: =IF($D68="","",IFERROR(INDEX(Mapping!$H$3:$H$32,MATCH($B68,Mapping!$G$3:$G$32,0)),IF(LEFT($F68,3)="P2P",IFERROR(INDEX(Mapping!$E$3:$E$6,MATCH($G68,Mapping!$D$3:$D$6,0)),IFERROR(INDEX(Mapping!$B$3:$B$13,MATCH($J68,Mapping!$A$3:$A$13,0)),"(unmapped)")),IFERROR(INDEX(Mapping!$B$17:$B$22,MATCH($F68,Mapping!$A$17:$A$22,0)),$F68)&" "&IF($G68="Banking","Banking",IFERROR(INDEX(Mapping!$E$17:$E$28,MATCH($J68,Mapping!$D$17:$D$28,0)),"(unmapped)"))))) -> R2R IB
A69: ES1101 | B69: 103016 | C69: KILA, JEFFREY | D69: AP09 | E69: 2026 | F69: P2P Vuelta | G69: Helpdesk | H69: DSS | I69: 1 | J69: NL | K69: =IF($D69="","",IFERROR(INDEX(Mapping!$H$3:$H$32,MATCH($B69,Mapping!$G$3:$G$32,0)),IF(LEFT($F69,3)="P2P",IFERROR(INDEX(Mapping!$E$3:$E$6,MATCH($G69,Mapping!$D$3:$D$6,0)),IFERROR(INDEX(Mapping!$B$3:$B$13,MATCH($J69,Mapping!$A$3:$A$13,0)),"(unmapped)")),IFERROR(INDEX(Mapping!$B$17:$B$22,MATCH($F69,Mapping!$A$17:$A$22,0)),$F69)&" "&IF($G69="Banking","Banking",IFERROR(INDEX(Mapping!$E$17:$E$28,MATCH($J69,Mapping!$D$17:$D$28,0)),"(unmapped)"))))) -> P2P Vuelta BE
A70: ES1101 | B70: 103018 | C70: DOMINGO LOZANO, ENRIQUE | D70: AP09 | E70: 2026 | F70: Q2C | H70: DSS | I70: 1 | J70: Iberia | K70: =IF($D70="","",IFERROR(INDEX(Mapping!$H$3:$H$32,MATCH($B70,Mapping!$G$3:$G$32,0)),IF(LEFT($F70,3)="P2P",IFERROR(INDEX(Mapping!$E$3:$E$6,MATCH($G70,Mapping!$D$3:$D$6,0)),IFERROR(INDEX(Mapping!$B$3:$B$13,MATCH($J70,Mapping!$A$3:$A$13,0)),"(unmapped)")),IFERROR(INDEX(Mapping!$B$17:$B$22,MATCH($F70,Mapping!$A$17:$A$22,0)),$F70)&" "&IF($G70="Banking","Banking",IFERROR(INDEX(Mapping!$E$17:$E$28,MATCH($J70,Mapping!$D$17:$D$28,0)),"(unmapped)"))))) -> AR IB
A71: ES1101 | B71: 103024 | C71: ALCALDE GEERDES, NOËMI | D71: AP09 | E71: 2026 | F71: Q2C | H71: IP | I71: 1 | J71: Iberia | K71: =IF($D71="","",IFERROR(INDEX(Mapping!$H$3:$H$32,MATCH($B71,Mapping!$G$3:$G$32,0)),IF(LEFT($F71,3)="P2P",IFERROR(INDEX(Mapping!$E$3:$E$6,MATCH($G71,Mapping!$D$3:$D$6,0)),IFERROR(INDEX(Mapping!$B$3:$B$13,MATCH($J71,Mapping!$A$3:$A$13,0)),"(unmapped)")),IFERROR(INDEX(Mapping!$B$17:$B$22,MATCH($F71,Mapping!$A$17:$A$22,0)),$F71)&" "&IF($G71="Banking","Banking",IFERROR(INDEX(Mapping!$E$17:$E$28,MATCH($J71,Mapping!$D$17:$D$28,0)),"(unmapped)"))))) -> AR IB
A72: ES1101 | B72: 103037 | C72: APOSTOL APOSTOL, GABRIELA | D72: AP09 | E72: 2026 | F72: Q2C | G72: Banking | H72: IP | I72: 1 | J72: Iberia | K72: =IF($D72="","",IFERROR(INDEX(Mapping!$H$3:$H$32,MATCH($B72,Mapping!$G$3:$G$32,0)),IF(LEFT($F72,3)="P2P",IFERROR(INDEX(Mapping!$E$3:$E$6,MATCH($G72,Mapping!$D$3:$D$6,0)),IFERROR(INDEX(Mapping!$B$3:$B$13,MATCH($J72,Mapping!$A$3:$A$13,0)),"(unmapped)")),IFERROR(INDEX(Mapping!$B$17:$B$22,MATCH($F72,Mapping!$A$17:$A$22,0)),$F72)&" "&IF($G72="Banking","Banking",IFERROR(INDEX(Mapping!$E$17:$E$28,MATCH($J72,Mapping!$D$17:$D$28,0)),"(unmapped)"))))) -> AR Banking
A73: ES1101 | B73: 103038 | C73: CAQUI BARRUETA, WALTER AARON | D73: AP09 | E73: 2026 | F73: P2P | H73: DSS | I73: 1 | J73: Iberia | K73: =IF($D73="","",IFERROR(INDEX(Mapping!$H$3:$H$32,MATCH($B73,Mapping!$G$3:$G$32,0)),IF(LEFT($F73,3)="P2P",IFERROR(INDEX(Mapping!$E$3:$E$6,MATCH($G73,Mapping!$D$3:$D$6,0)),IFERROR(INDEX(Mapping!$B$3:$B$13,MATCH($J73,Mapping!$A$3:$A$13,0)),"(unmapped)")),IFERROR(INDEX(Mapping!$B$17:$B$22,MATCH($F73,Mapping!$A$17:$A$22,0)),$F73)&" "&IF($G73="Banking","Banking",IFERROR(INDEX(Mapping!$E$17:$E$28,MATCH($J73,Mapping!$D$17:$D$28,0)),"(unmapped)"))))) -> AP IB
A74: ES1101 | B74: 103039 | C74: ARROYO MATESANZ, ALEJANDRO | D74: AP09 | E74: 2026 | F74: R2R | H74: IP | I74: 1 | J74: Iberia | K74: =IF($D74="","",IFERROR(INDEX(Mapping!$H$3:$H$32,MATCH($B74,Mapping!$G$3:$G$32,0)),IF(LEFT($F74,3)="P2P",IFERROR(INDEX(Mapping!$E$3:$E$6,MATCH($G74,Mapping!$D$3:$D$6,0)),IFERROR(INDEX(Mapping!$B$3:$B$13,MATCH($J74,Mapping!$A$3:$A$13,0)),"(unmapped)")),IFERROR(INDEX(Mapping!$B$17:$B$22,MATCH($F74,Mapping!$A$17:$A$22,0)),$F74)&" "&IF($G74="Banking","Banking",IFERROR(INDEX(Mapping!$E$17:$E$28,MATCH($J74,Mapping!$D$17:$D$28,0)),"(unmapped)"))))) -> R2R IB
A75: ES1101 | B75: 103064 | C75: IMAZ MATEOS, OLAYA | D75: AP09 | E75: 2026 | F75: R2R | H75: DSS | I75: 1 | J75: Kunheim | K75: =IF($D75="","",IFERROR(INDEX(Mapping!$H$3:$H$32,MATCH($B75,Mapping!$G$3:$G$32,0)),IF(LEFT($F75,3)="P2P",IFERROR(INDEX(Mapping!$E$3:$E$6,MATCH($G75,Mapping!$D$3:$D$6,0)),IFERROR(INDEX(Mapping!$B$3:$B$13,MATCH($J75,Mapping!$A$3:$A$13,0)),"(unmapped)")),IFERROR(INDEX(Mapping!$B$17:$B$22,MATCH($F75,Mapping!$A$17:$A$22,0)),$F75)&" "&IF($G75="Banking","Banking",IFERROR(INDEX(Mapping!$E$17:$E$28,MATCH($J75,Mapping!$D$17:$D$28,0)),"(unmapped)"))))) -> R2R Kunheim
A76: ES1101 | B76: 103118 | C76: RIU ALVAREZ, CRISTINA | D76: AP09 | E76: 2026 | F76: OoS | H76: Out Scope | I76: 1 | J76: Graduate | K76: =IF($D76="","",IFERROR(INDEX(Mapping!$H$3:$H$32,MATCH($B76,Mapping!$G$3:$G$32,0)),IF(LEFT($F76,3)="P2P",IFERROR(INDEX(Mapping!$E$3:$E$6,MATCH($G76,Mapping!$D$3:$D$6,0)),IFERROR(INDEX(Mapping!$B$3:$B$13,MATCH($J76,Mapping!$A$3:$A$13,0)),"(unmapped)")),IFERROR(INDEX(Mapping!$B$17:$B$22,MATCH($F76,Mapping!$A$17:$A$22,0)),$F76)&" "&IF($G76="Banking","Banking",IFERROR(INDEX(Mapping!$E$17:$E$28,MATCH($J76,Mapping!$D$17:$D$28,0)),"(unmapped)"))))) -> OoS (unmapped)
A77: ES1101 | B77: 103119 | C77: HERNANDEZ MARTIN, MIGUEL | D77: AP09 | E77: 2026 | F77: R2R | H77: IP | I77: 1 | J77: Iberia | K77: =IF($D77="","",IFERROR(INDEX(Mapping!$H$3:$H$32,MATCH($B77,Mapping!$G$3:$G$32,0)),IF(LEFT($F77,3)="P2P",IFERROR(INDEX(Mapping!$E$3:$E$6,MATCH($G77,Mapping!$D$3:$D$6,0)),IFERROR(INDEX(Mapping!$B$3:$B$13,MATCH($J77,Mapping!$A$3:$A$13,0)),"(unmapped)")),IFERROR(INDEX(Mapping!$B$17:$B$22,MATCH($F77,Mapping!$A$17:$A$22,0)),$F77)&" "&IF($G77="Banking","Banking",IFERROR(INDEX(Mapping!$E$17:$E$28,MATCH($J77,Mapping!$D$17:$D$28,0)),"(unmapped)"))))) -> R2R IB
A78: ES1101 | B78: 103152 | C78: LABRADOR SIMON, GONZALO | D78: AP09 | E78: 2026 | F78: P2P | H78: IP | I78: 1 | J78: Iberia | K78: =IF($D78="","",IFERROR(INDEX(Mapping!$H$3:$H$32,MATCH($B78,Mapping!$G$3:$G$32,0)),IF(LEFT($F78,3)="P2P",IFERROR(INDEX(Mapping!$E$3:$E$6,MATCH($G78,Mapping!$D$3:$D$6,0)),IFERROR(INDEX(Mapping!$B$3:$B$13,MATCH($J78,Mapping!$A$3:$A$13,0)),"(unmapped)")),IFERROR(INDEX(Mapping!$B$17:$B$22,MATCH($F78,Mapping!$A$17:$A$22,0)),$F78)&" "&IF($G78="Banking","Banking",IFERROR(INDEX(Mapping!$E$17:$E$28,MATCH($J78,Mapping!$D$17:$D$28,0)),"(unmapped)"))))) -> AP IB
A79: ES1101 | B79: 103156 | C79: ARCE IBAÑEZ, MARIO | D79: AP09 | E79: 2026 | F79: P2P Vuelta | H79: DSS | I79: 1 | J79: UK | K79: =IF($D79="","",IFERROR(INDEX(Mapping!$H$3:$H$32,MATCH($B79,Mapping!$G$3:$G$32,0)),IF(LEFT($F79,3)="P2P",IFERROR(INDEX(Mapping!$E$3:$E$6,MATCH($G79,Mapping!$D$3:$D$6,0)),IFERROR(INDEX(Mapping!$B$3:$B$13,MATCH($J79,Mapping!$A$3:$A$13,0)),"(unmapped)")),IFERROR(INDEX(Mapping!$B$17:$B$22,MATCH($F79,Mapping!$A$17:$A$22,0)),$F79)&" "&IF($G79="Banking","Banking",IFERROR(INDEX(Mapping!$E$17:$E$28,MATCH($J79,Mapping!$D$17:$D$28,0)),"(unmapped)"))))) -> P2P Vuelta UK
A80: ES1101 | B80: 103157 | C80: PENA ANNUNZIATA, ANDREA VICTORIA | D80: AP09 | E80: 2026 | F80: P2P | H80: IP | I80: 1 | J80: IT | K80: =IF($D80="","",IFERROR(INDEX(Mapping!$H$3:$H$32,MATCH($B80,Mapping!$G$3:$G$32,0)),IF(LEFT($F80,3)="P2P",IFERROR(INDEX(Mapping!$E$3:$E$6,MATCH($G80,Mapping!$D$3:$D$6,0)),IFERROR(INDEX(Mapping!$B$3:$B$13,MATCH($J80,Mapping!$A$3:$A$13,0)),"(unmapped)")),IFERROR(INDEX(Mapping!$B$17:$B$22,MATCH($F80,Mapping!$A$17:$A$22,0)),$F80)&" "&IF($G80="Banking","Banking",IFERROR(INDEX(Mapping!$E$17:$E$28,MATCH($J80,Mapping!$D$17:$D$28,0)),"(unmapped)"))))) -> AP IT
A81: ES1101 | B81: 103193 | C81: MARTINEZ PALLIN, ALEJANDRO | D81: AP09 | E81: 2026 | F81: P2P Vuelta | H81: DSS | I81: 1 | J81: DE | K81: =IF($D81="","",IFERROR(INDEX(Mapping!$H$3:$H$32,MATCH($B81,Mapping!$G$3:$G$32,0)),IF(LEFT($F81,3)="P2P",IFERROR(INDEX(Mapping!$E$3:$E$6,MATCH($G81,Mapping!$D$3:$D$6,0)),IFERROR(INDEX(Mapping!$B$3:$B$13,MATCH($J81,Mapping!$A$3:$A$13,0)),"(unmapped)")),IFERROR(INDEX(Mapping!$B$17:$B$22,MATCH($F81,Mapping!$A$17:$A$22,0)),$F81)&" "&IF($G81="Banking","Banking",IFERROR(INDEX(Mapping!$E$17:$E$28,MATCH($J81,Mapping!$D$17:$D$28,0)),"(unmapped)"))))) -> P2P Vuelta DE
A82: ES1101 | B82: 103197 | C82: VULCANO SORIANO, ROCIO | D82: AP09 | E82: 2026 | F82: Q2C | H82: IP | I82: 1 | J82: Iberia | K82: =IF($D82="","",IFERROR(INDEX(Mapping!$H$3:$H$32,MATCH($B82,Mapping!$G$3:$G$32,0)),IF(LEFT($F82,3)="P2P",IFERROR(INDEX(Mapping!$E$3:$E$6,MATCH($G82,Mapping!$D$3:$D$6,0)),IFERROR(INDEX(Mapping!$B$3:$B$13,MATCH($J82,Mapping!$A$3:$A$13,0)),"(unmapped)")),IFERROR(INDEX(Mapping!$B$17:$B$22,MATCH($F82,Mapping!$A$17:$A$22,0)),$F82)&" "&IF($G82="Banking","Banking",IFERROR(INDEX(Mapping!$E$17:$E$28,MATCH($J82,Mapping!$D$17:$D$28,0)),"(unmapped)"))))) -> AR IB
A83: ES1101 | B83: 103217 | C83: LOZANO DE CASTRO, RAUL | D83: AP09 | E83: 2026 | F83: P2P Vuelta | H83: DSS | I83: 1 | J83: UK | K83: =IF($D83="","",IFERROR(INDEX(Mapping!$H$3:$H$32,MATCH($B83,Mapping!$G$3:$G$32,0)),IF(LEFT($F83,3)="P2P",IFERROR(INDEX(Mapping!$E$3:$E$6,MATCH($G83,Mapping!$D$3:$D$6,0)),IFERROR(INDEX(Mapping!$B$3:$B$13,MATCH($J83,Mapping!$A$3:$A$13,0)),"(unmapped)")),IFERROR(INDEX(Mapping!$B$17:$B$22,MATCH($F83,Mapping!$A$17:$A$22,0)),$F83)&" "&IF($G83="Banking","Banking",IFERROR(INDEX(Mapping!$E$17:$E$28,MATCH($J83,Mapping!$D$17:$D$28,0)),"(unmapped)"))))) -> P2P Vuelta UK
A84: ES1101 | B84: 103222 | C84: HERNANDEZ DOMINGUEZ, PAULA | D84: AP09 | E84: 2026 | F84: P2P Vuelta | H84: DSS | I84: 0.8125 | J84: FR | K84: =IF($D84="","",IFERROR(INDEX(Mapping!$H$3:$H$32,MATCH($B84,Mapping!$G$3:$G$32,0)),IF(LEFT($F84,3)="P2P",IFERROR(INDEX(Mapping!$E$3:$E$6,MATCH($G84,Mapping!$D$3:$D$6,0)),IFERROR(INDEX(Mapping!$B$3:$B$13,MATCH($J84,Mapping!$A$3:$A$13,0)),"(unmapped)")),IFERROR(INDEX(Mapping!$B$17:$B$22,MATCH($F84,Mapping!$A$17:$A$22,0)),$F84)&" "&IF($G84="Banking","Banking",IFERROR(INDEX(Mapping!$E$17:$E$28,MATCH($J84,Mapping!$D$17:$D$28,0)),"(unmapped)"))))) -> P2P Vuelta FR
... A89: ES1101 | B89: 103279 | C89: PEREZ CALDERON, JAVIER | D89: AP09 | E89: 2026 | F89: R2R | H89: DSS | I89: 1 | J89: Iberia | K89: =IF($D89="","",IFERROR(INDEX(Mapping!$H$3:$H$32,MATCH($B89,Mapping!$G$3:$G$32,0)),IF(LEFT($F89,3)="P2P",IFERROR(INDEX(Mapping!$E$3:$E$6,MATCH($G89,Mapping!$D$3:$D$6,0)),IFERROR(INDEX(Mapping!$B$3:$B$13,MATCH($J89,Mapping!$A$3:$A$13,0)),"(unmapped)")),IFERROR(INDEX(Mapping!$B$17:$B$22,MATCH($F89,Mapping!$A$17:$A$22,0)),$F89)&" "&IF($G89="Banking","Banking",IFERROR(INDEX(Mapping!$E$17:$E$28,MATCH($J89,Mapping!$D$17:$D$28,0)),"(unmapped)"))))) -> R2R IB
A90: ES1101 | B90: 103282 | C90: VIEIRA PALOMINO, MAYARA FERNANDA | D90: AP09 | E90: 2026 | F90: P2P | G90: Helpdesk | H90: DSS | I90: 1 | J90: Iberia | K90: =IF($D90="","",IFERROR(INDEX(Mapping!$H$3:$H$32,MATCH($B90,Mapping!$G$3:$G$32,0)),IF(LEFT($F90,3)="P2P",IFERROR(INDEX(Mapping!$E$3:$E$6,MATCH($G90,Mapping!$D$3:$D$6,0)),IFERROR(INDEX(Mapping!$B$3:$B$13,MATCH($J90,Mapping!$A$3:$A$13,0)),"(unmapped)")),IFERROR(INDEX(Mapping!$B$17:$B$22,MATCH($F90,Mapping!$A$17:$A$22,0)),$F90)&" "&IF($G90="Banking","Banking",IFERROR(INDEX(Mapping!$E$17:$E$28,MATCH($J90,Mapping!$D$17:$D$28,0)),"(unmapped)"))))) -> AP Help Desk
A91: ES1101 | B91: 103283 | C91: ESCUDERO PIÑEYROA, JORGE | D91: AP09 | E91: 2026 | F91: P2P Vuelta | H91: DSS | I91: 1 | J91: FR | K91: =IF($D91="","",IFERROR(INDEX(Mapping!$H$3:$H$32,MATCH($B91,Mapping!$G$3:$G$32,0)),IF(LEFT($F91,3)="P2P",IFERROR(INDEX(Mapping!$E$3:$E$6,MATCH($G91,Mapping!$D$3:$D$6,0)),IFERROR(INDEX(Mapping!$B$3:$B$13,MATCH($J91,Mapping!$A$3:$A$13,0)),"(unmapped)")),IFERROR(INDEX(Mapping!$B$17:$B$22,MATCH($F91,Mapping!$A$17:$A$22,0)),$F91)&" "&IF($G91="Banking","Banking",IFERROR(INDEX(Mapping!$E$17:$E$28,MATCH($J91,Mapping!$D$17:$D$28,0)),"(unmapped)"))))) -> P2P Vuelta FR
A92: ES1101 | B92: 103284 | C92: GARCIA SAN JOSE, JAVIER | D92: AP09 | E92: 2026 | F92: Q2C | H92: IP | I92: 1 | J92: Iberia | K92: =IF($D92="","",IFERROR(INDEX(Mapping!$H$3:$H$32,MATCH($B92,Mapping!$G$3:$G$32,0)),IF(LEFT($F92,3)="P2P",IFERROR(INDEX(Mapping!$E$3:$E$6,MATCH($G92,Mapping!$D$3:$D$6,0)),IFERROR(INDEX(Mapping!$B$3:$B$13,MATCH($J92,Mapping!$A$3:$A$13,0)),"(unmapped)")),IFERROR(INDEX(Mapping!$B$17:$B$22,MATCH($F92,Mapping!$A$17:$A$22,0)),$F92)&" "&IF($G92="Banking","Banking",IFERROR(INDEX(Mapping!$E$17:$E$28,MATCH($J92,Mapping!$D$17:$D$28,0)),"(unmapped)"))))) -> AR IB
A93: ES1101 | B93: 103285 | C93: GAGO MIGUEL, PAULA | D93: AP09 | E93: 2026 | F93: P2P Vuelta | H93: DSS | I93: 1 | J93: FR | K93: =IF($D93="","",IFERROR(INDEX(Mapping!$H$3:$H$32,MATCH($B93,Mapping!$G$3:$G$32,0)),IF(LEFT($F93,3)="P2P",IFERROR(INDEX(Mapping!$E$3:$E$6,MATCH($G93,Mapping!$D$3:$D$6,0)),IFERROR(INDEX(Mapping!$B$3:$B$13,MATCH($J93,Mapping!$A$3:$A$13,0)),"(unmapped)")),IFERROR(INDEX(Mapping!$B$17:$B$22,MATCH($F93,Mapping!$A$17:$A$22,0)),$F93)&" "&IF($G93="Banking","Banking",IFERROR(INDEX(Mapping!$E$17:$E$28,MATCH($J93,Mapping!$D$17:$D$28,0)),"(unmapped)"))))) -> P2P Vuelta FR
A94: ES1101 | B94: 103297 | C94: ESCORIHUELA EIZAGA, ISMENIA INDIRA | D94: AP09 | E94: 2026 | F94: R2R | H94: IP | I94: 1 | J94: Iberia | K94: =IF($D94="","",IFERROR(INDEX(Mapping!$H$3:$H$32,MATCH($B94,Mapping!$G$3:$G$32,0)),IF(LEFT($F94,3)="P2P",IFERROR(INDEX(Mapping!$E$3:$E$6,MATCH($G94,Mapping!$D$3:$D$6,0)),IFERROR(INDEX(Mapping!$B$3:$B$13,MATCH($J94,Mapping!$A$3:$A$13,0)),"(unmapped)")),IFERROR(INDEX(Mapping!$B$17:$B$22,MATCH($F94,Mapping!$A$17:$A$22,0)),$F94)&" "&IF($G94="Banking","Banking",IFERROR(INDEX(Mapping!$E$17:$E$28,MATCH($J94,Mapping!$D$17:$D$28,0)),"(unmapped)"))))) -> R2R IB
A95: ES1101 | B95: 103299 | C95: POSADAS GAÑAN, PAULA | D95: AP09 | E95: 2026 | F95: P2P | H95: IP | I95: 1 | J95: Iberia | K95: =IF($D95="","",IFERROR(INDEX(Mapping!$H$3:$H$32,MATCH($B95,Mapping!$G$3:$G$32,0)),IF(LEFT($F95,3)="P2P",IFERROR(INDEX(Mapping!$E$3:$E$6,MATCH($G95,Mapping!$D$3:$D$6,0)),IFERROR(INDEX(Mapping!$B$3:$B$13,MATCH($J95,Mapping!$A$3:$A$13,0)),"(unmapped)")),IFERROR(INDEX(Mapping!$B$17:$B$22,MATCH($F95,Mapping!$A$17:$A$22,0)),$F95)&" "&IF($G95="Banking","Banking",IFERROR(INDEX(Mapping!$E$17:$E$28,MATCH($J95,Mapping!$D$17:$D$28,0)),"(unmapped)"))))) -> AP IB
A96: ES1101 | B96: 103300 | C96: PEÑA MORAN, RUBÉN | D96: AP09 | E96: 2026 | F96: Q2C | H96: IP | I96: 1 | J96: Iberia | K96: =IF($D96="","",IFERROR(INDEX(Mapping!$H$3:$H$32,MATCH($B96,Mapping!$G$3:$G$32,0)),IF(LEFT($F96,3)="P2P",IFERROR(INDEX(Mapping!$E$3:$E$6,MATCH($G96,Mapping!$D$3:$D$6,0)),IFERROR(INDEX(Mapping!$B$3:$B$13,MATCH($J96,Mapping!$A$3:$A$13,0)),"(unmapped)")),IFERROR(INDEX(Mapping!$B$17:$B$22,MATCH($F96,Mapping!$A$17:$A$22,0)),$F96)&" "&IF($G96="Banking","Banking",IFERROR(INDEX(Mapping!$E$17:$E$28,MATCH($J96,Mapping!$D$17:$D$28,0)),"(unmapped)"))))) -> AR IB
A97: ES1101 | B97: 103304 | C97: CAMINO FOMBELLIDA, IRENE | D97: AP09 | E97: 2026 | F97: Q2C | H97: IP | I97: 1 | J97: Iberia | K97: =IF($D97="","",IFERROR(INDEX(Mapping!$H$3:$H$32,MATCH($B97,Mapping!$G$3:$G$32,0)),IF(LEFT($F97,3)="P2P",IFERROR(INDEX(Mapping!$E$3:$E$6,MATCH($G97,Mapping!$D$3:$D$6,0)),IFERROR(INDEX(Mapping!$B$3:$B$13,MATCH($J97,Mapping!$A$3:$A$13,0)),"(unmapped)")),IFERROR(INDEX(Mapping!$B$17:$B$22,MATCH($F97,Mapping!$A$17:$A$22,0)),$F97)&" "&IF($G97="Banking","Banking",IFERROR(INDEX(Mapping!$E$17:$E$28,MATCH($J97,Mapping!$D$17:$D$28,0)),"(unmapped)"))))) -> AR IB
A98: ES1101 | B98: 103311 | C98: LEZCANO MAMBRILLA, JIMENA | D98: AP09 | E98: 2026 | F98: R2R | H98: DSS | I98: 1 | J98: Iberia | K98: =IF($D98="","",IFERROR(INDEX(Mapping!$H$3:$H$32,MATCH($B98,Mapping!$G$3:$G$32,0)),IF(LEFT($F98,3)="P2P",IFERROR(INDEX(Mapping!$E$3:$E$6,MATCH($G98,Mapping!$D$3:$D$6,0)),IFERROR(INDEX(Mapping!$B$3:$B$13,MATCH($J98,Mapping!$A$3:$A$13,0)),"(unmapped)")),IFERROR(INDEX(Mapping!$B$17:$B$22,MATCH($F98,Mapping!$A$17:$A$22,0)),$F98)&" "&IF($G98="Banking","Banking",IFERROR(INDEX(Mapping!$E$17:$E$28,MATCH($J98,Mapping!$D$17:$D$28,0)),"(unmapped)"))))) -> R2R IB
A99: ES1101 | B99: 103313 | C99: REBOLLO GOMEZ, PAULA | D99: AP09 | E99: 2026 | F99: P2P Vuelta | G99: Helpdesk | H99: DSS | I99: 1 | J99: DE | K99: =IF($D99="","",IFERROR(INDEX(Mapping!$H$3:$H$32,MATCH($B99,Mapping!$G$3:$G$32,0)),IF(LEFT($F99,3)="P2P",IFERROR(INDEX(Mapping!$E$3:$E$6,MATCH($G99,Mapping!$D$3:$D$6,0)),IFERROR(INDEX(Mapping!$B$3:$B$13,MATCH($J99,Mapping!$A$3:$A$13,0)),"(unmapped)")),IFERROR(INDEX(Mapping!$B$17:$B$22,MATCH($F99,Mapping!$A$17:$A$22,0)),$F99)&" "&IF($G99="Banking","Banking",IFERROR(INDEX(Mapping!$E$17:$E$28,MATCH($J99,Mapping!$D$17:$D$28,0)),"(unmapped)"))))) -> P2P Vuelta DE
A100: ES1101 | B100: 103314 | C100: FERNANDEZ PRIETO, PAULA | D100: AP09 | E100: 2026 | F100: P2P | H100: IP | I100: 1 | J100: MA | K100: =IF($D100="","",IFERROR(INDEX(Mapping!$H$3:$H$32,MATCH($B100,Mapping!$G$3:$G$32,0)),IF(LEFT($F100,3)="P2P",IFERROR(INDEX(Mapping!$E$3:$E$6,MATCH($G100,Mapping!$D$3:$D$6,0)),IFERROR(INDEX(Mapping!$B$3:$B$13,MATCH($J100,Mapping!$A$3:$A$13,0)),"(unmapped)")),IFERROR(INDEX(Mapping!$B$17:$B$22,MATCH($F100,Mapping!$A$17:$A$22,0)),$F100)&" "&IF($G100="Banking","Banking",IFERROR(INDEX(Mapping!$E$17:$E$28,MATCH($J100,Mapping!$D$17:$D$28,0)),"(unmapped)"))))) -> AP MA
A101: ES1101 | B101: 103315 | C101: BARBADO DIEZ, CARMEN | D101: AP09 | E101: 2026 | F101: R2R | H101: IP | I101: 1 | J101: Iberia | K101: =IF($D101="","",IFERROR(INDEX(Mapping!$H$3:$H$32,MATCH($B101,Mapping!$G$3:$G$32,0)),IF(LEFT($F101,3)="P2P",IFERROR(INDEX(Mapping!$E$3:$E$6,MATCH($G101,Mapping!$D$3:$D$6,0)),IFERROR(INDEX(Mapping!$B$3:$B$13,MATCH($J101,Mapping!$A$3:$A$13,0)),"(unmapped)")),IFERROR(INDEX(Mapping!$B$17:$B$22,MATCH($F101,Mapping!$A$17:$A$22,0)),$F101)&" "&IF($G101="Banking","Banking",IFERROR(INDEX(Mapping!$E$17:$E$28,MATCH($J101,Mapping!$D$17:$D$28,0)),"(unmapped)"))))) -> R2R IB
A102: ES1101 | B102: 103336 | C102: MACI, MICHELE | D102: AP09 | E102: 2026 | F102: Q2C | H102: IP | I102: 1 | J102: Iberia | K102: =IF($D102="","",IFERROR(INDEX(Mapping!$H$3:$H$32,MATCH($B102,Mapping!$G$3:$G$32,0)),IF(LEFT($F102,3)="P2P",IFERROR(INDEX(Mapping!$E$3:$E$6,MATCH($G102,Mapping!$D$3:$D$6,0)),IFERROR(INDEX(Mapping!$B$3:$B$13,MATCH($J102,Mapping!$A$3:$A$13,0)),"(unmapped)")),IFERROR(INDEX(Mapping!$B$17:$B$22,MATCH($F102,Mapping!$A$17:$A$22,0)),$F102)&" "&IF($G102="Banking","Banking",IFERROR(INDEX(Mapping!$E$17:$E$28,MATCH($J102,Mapping!$D$17:$D$28,0)),"(unmapped)"))))) -> AR IB
A103: ES1101 | B103: 103317 | C103: GARCIA HERNANDEZ, CARLA | D103: AP09 | E103: 2026 | F103: R2R | H103: IP | I103: 1 | J103: Iberia | K103: =IF($D103="","",IFERROR(INDEX(Mapping!$H$3:$H$32,MATCH($B103,Mapping!$G$3:$G$32,0)),IF(LEFT($F103,3)="P2P",IFERROR(INDEX(Mapping!$E$3:$E$6,MATCH($G103,Mapping!$D$3:$D$6,0)),IFERROR(INDEX(Mapping!$B$3:$B$13,MATCH($J103,Mapping!$A$3:$A$13,0)),"(unmapped)")),IFERROR(INDEX(Mapping!$B$17:$B$22,MATCH($F103,Mapping!$A$17:$A$22,0)),$F103)&" "&IF($G103="Banking","Banking",IFERROR(INDEX(Mapping!$E$17:$E$28,MATCH($J103,Mapping!$D$17:$D$28,0)),"(unmapped)"))))) -> R2R IB
A104: ES1101 | B104: 103319 | C104: GARCIA-ROJO MARTORELL, CRISTINA | D104: AP09 | E104: 2026 | F104: Q2C | H104: IP | I104: 1 | J104: Iberia | K104: =IF($D104="","",IFERROR(INDEX(Mapping!$H$3:$H$32,MATCH($B104,Mapping!$G$3:$G$32,0)),IF(LEFT($F104,3)="P2P",IFERROR(INDEX(Mapping!$E$3:$E$6,MATCH($G104,Mapping!$D$3:$D$6,0)),IFERROR(INDEX(Mapping!$B$3:$B$13,MATCH($J104,Mapping!$A$3:$A$13,0)),"(unmapped)")),IFERROR(INDEX(Mapping!$B$17:$B$22,MATCH($F104,Mapping!$A$17:$A$22,0)),$F104)&" "&IF($G104="Banking","Banking",IFERROR(INDEX(Mapping!$E$17:$E$28,MATCH($J104,Mapping!$D$17:$D$28,0)),"(unmapped)"))))) -> AR IB
...

Sheet DIV table
A1: Label | B1: Div | C1: Subdivisión | E1: This table is the one that organises the divisions
A2: DE_Pack | B2: DE | C2: DE
A3: FR_Qualiac | B3: FR | C3: FR
A4: FR_Navision | B4: FR | C4: FR
A5: IT_Paper | B5: IT | C5: IT
A6: BE_Pack | B6: BE | C6: BE
A7: NL_Pack | B7: BE | C7: BE
A8: NL_PMS | B8: PMS | C8: PMS
A9: UK_TMS | B9: TMS | C9: TMS
A10: NL_Paper | B10: PS | C10: PS
A11: UK_Pack | B11: UK | C11: UK
A12: UK_Paper | B12: UK | C12: UK
A13: UK_PLC | B13: UK | C13: UK
... A23: Paper FR | B23: - | C23: FR

Sheet Mapping
A1: P2P only: Team → AP category | D1: P2P only: Sub-process → AP category | G1: EXCEPTIONS by employee (highest priority)
A2: Team | B2: Category | D2: Sub-process | E2: Category | G2: Employee no. | H2: Category | I2: Name (auto)
A3: DE | B3: AP DE | D3: Banking | E3: Banking | I3: =IF($G3="","",IFERROR(INDEX(Payroll!$C:$C,MATCH($G3,Payroll!$B:$B,0)),"(not found)"))
A4: FR | B4: AP FR | D4: Helpdesk | E4: AP Help Desk | I4: =IF($G4="","",IFERROR(INDEX(Payroll!$C:$C,MATCH($G4,Payroll!$B:$B,0)),"(not found)"))
A5: Iberia | B5: AP IB | D5: Manager | E5: AP Manager | I5: =IF($G5="","",IFERROR(INDEX(Payroll!$C:$C,MATCH($G5,Payroll!$B:$B,0)),"(not found)"))
A6: UK | B6: AP UK | D6: General | E6: AP General | I6: =IF($G6="","",IFERROR(INDEX(Payroll!$C:$C,MATCH($G6,Payroll!$B:$B,0)),"(not found)"))
A7: Benelux | B7: AP BE | I7: =IF($G7="","",IFERROR(INDEX(Payroll!$C:$C,MATCH($G7,Payroll!$B:$B,0)),"(not found)"))
A8: IT | B8: AP IT | I8: =IF($G8="","",IFERROR(INDEX(Payroll!$C:$C,MATCH($G8,Payroll!$B:$B,0)),"(not found)"))
A9: PS | B9: AP PS | I9: =IF($G9="","",IFERROR(INDEX(Payroll!$C:$C,MATCH($G9,Payroll!$B:$B,0)),"(not found)"))
A10: General | B10: AP General | I10: =IF($G10="","",IFERROR(INDEX(Payroll!$C:$C,MATCH($G10,Payroll!$B:$B,0)),"(not found)"))
A11: Mejora | B11: AP Continuos improvement | I11: =IF($G11="","",IFERROR(INDEX(Payroll!$C:$C,MATCH($G11,Payroll!$B:$B,0)),"(not found)"))
A12: MA | B12: AP MA | I12: =IF($G12="","",IFERROR(INDEX(Payroll!$C:$C,MATCH($G12,Payroll!$B:$B,0)),"(not found)"))
A13: NL | B13: AP BE | I13: =IF($G13="","",IFERROR(INDEX(Payroll!$C:$C,MATCH($G13,Payroll!$B:$B,0)),"(not found)"))
I14: =IF($G14="","",IFERROR(INDEX(Payroll!$C:$C,MATCH($G14,Payroll!$B:$B,0)),"(not found)"))
A15: Other processes: Process → label | D15: Other processes: Team → country code | I15: =IF($G15="","",IFERROR(INDEX(Payroll!$C:$C,MATCH($G15,Payroll!$B:$B,0)),"(not found)"))
A16: Process | B16: Label | D16: Team | E16: Country | I16: =IF($G16="","",IFERROR(INDEX(Payroll!$C:$C,MATCH($G16,Payroll!$B:$B,0)),"(not found)"))
A17: Q2C | B17: AR | D17: Iberia | E17: IB | I17: =IF($G17="","",IFERROR(INDEX(Payroll!$C:$C,MATCH($G17,Payroll!$B:$B,0)),"(not found)"))
A18: O2C | B18: AR | D18: FR | E18: FR | I18: =IF($G18="","",IFERROR(INDEX(Payroll!$C:$C,MATCH($G18,Payroll!$B:$B,0)),"(not found)"))
A19: R2R | B19: R2R | D19: IT | E19: IT | I19: =IF($G19="","",IFERROR(INDEX(Payroll!$C:$C,MATCH($G19,Payroll!$B:$B,0)),"(not found)"))
A20: HR | B20: HR | D20: MA | E20: MA | I20: =IF($G20="","",IFERROR(INDEX(Payroll!$C:$C,MATCH($G20,Payroll!$B:$B,0)),"(not found)"))
A21: DM | B21: MD | D21: DE | E21: DE | I21: =IF($G21="","",IFERROR(INDEX(Payroll!$C:$C,MATCH($G21,Payroll!$B:$B,0)),"(not found)"))
A22: OoS | B22: OoS | D22: UK | E22: UK | I22: =IF($G22="","",IFERROR(INDEX(Payroll!$C:$C,MATCH($G22,Payroll!$B:$B,0)),"(not found)"))
D23: Benelux | E23: BE | I23: =IF($G23="","",IFERROR(INDEX(Payroll!$C:$C,MATCH($G23,Payroll!$B:$B,0)),"(not found)"))
D24: NL | E24: BE | I24: =IF($G24="","",IFERROR(INDEX(Payroll!$C:$C,MATCH($G24,Payroll!$B:$B,0)),"(not found)"))
D25: PS | E25: PS | I25: =IF($G25="","",IFERROR(INDEX(Payroll!$C:$C,MATCH($G25,Payroll!$B:$B,0)),"(not found)"))
D26: Kunheim | E26: Kunheim | I26: =IF($G26="","",IFERROR(INDEX(Payroll!$C:$C,MATCH($G26,Payroll!$B:$B,0)),"(not found)"))
D27: Mejora | E27: Improvement | I27: =IF($G27="","",IFERROR(INDEX(Payroll!$C:$C,MATCH($G27,Payroll!$B:$B,0)),"(not found)"))
D28: General | E28: General | I28: =IF($G28="","",IFERROR(INDEX(Payroll!$C:$C,MATCH($G28,Payroll!$B:$B,0)),"(not found)"))
I29: =IF($G29="","",IFERROR(INDEX(Payroll!$C:$C,MATCH($G29,Payroll!$B:$B,0)),"(not found)"))
I30: =IF($G30="","",IFERROR(INDEX(Payroll!$C:$C,MATCH($G30,Payroll!$B:$B,0)),"(not found)"))
I31: =IF($G31="","",IFERROR(INDEX(Payroll!$C:$C,MATCH($G31,Payroll!$B:$B,0)),"(not found)"))
I32: =IF($G32="","",IFERROR(INDEX(Payroll!$C:$C,MATCH($G32,Payroll!$B:$B,0)),"(not found)"))

Sheet Instrucciones
A1: INSTRUCCIONES · Control mensual de FTE (el libro está en inglés)
A3: Qué hace este fichero
A4: Compara, para el periodo elegido, los FTE que constan en la NÓMINA ('Payroll') con los FTE reportados en el SCORECARD, por proceso (P2P/AP, AR, R2R) y por país. La diferencia se calcula sola y se marca con un semáforo.
A6: Uso mensual (2 pasos)
A7: 1. Actualiza los datos: pega la nómina del mes en la hoja 'Payroll' y actualiza la hoja 'FTE Scorecard', cambiar el filtro por el mes actual en la consulta combinar 2
A8: 2. En 'FTE Reconciliation' escribe el periodo en la celda I1 (p. ej. AP07) y el año en K1. Todo se recalcula solo.
A10: Hojas del libro
A11: Hoja | B11: Para qué sirve | C11: ¿La tocas?
A12: FTE Reconciliation | B12: Cuadre del negocio DSS (BAU). Hoja de presentación. | C12: Solo I1 (periodo) y K1 (año), más las columnas amarillas C, D y E.
A13: IP Reconciliation | B13: Mismo cuadre para el negocio IP. Aún no hay Scorecard de IP: la columna F (FTE Scorecard) es entrada manual hasta que llegue. | C13: I1, K1 y las columnas amarillas C, D, E y F.
A14: Payroll | B14: Detalle por persona. La columna K clasifica sola cada persona. | C14: Pegar los datos del mes (columnas A a J).
A15: FTE Scorecard | B15: FTE reportados por país, mes y definición. | C15: Pegar / actualizar.
A16: Mapping | B16: Reglas que traducen cada persona a su fila de la hoja de cuadre. | C16: Solo al cambiar equipos o funciones.
A17: Summary | B17: Análisis previo, se conserva como referencia. | C17: No.
A18: DIV table | B18: Tabla auxiliar de divisiones. | C18: No.
A20: Cómo se leen las columnas de la hoja de cuadre
A21: Columna | B21: Significado
A22: B · Payroll FTE | B22: Personas en nómina del periodo (se extrae de la hoja 'Payroll'). Fórmula: no tocar.
A23: C · Vacancy | B23: Vacantes. Entrada manual.
A24: D · Sick leave | B24: Bajas. Entrada manual.
A25: E · Adjustment | B25: Ajustes. Entrada manual.
A26: F · FTE Scorecard | B26: FTE reportados en el Scorecard. Fórmula: no tocar.
A27: H a L · Breakdown | B27: Reparto del FTE del Scorecard por rol. Entrada manual.
A28: M · Difference | B28: Descuadre: C + D + E + F − B.
A29: N · Status | B29: Semáforo automático: OK si la diferencia está dentro de ±0,02; Review en el resto de casos.
A30: O · Comments | B30: Justificación de la diferencia. Entrada manual.
A31: Color de M | B31: Verde: la diferencia está dentro de ±0,02 (cuadra). Rojo: fuera de ese margen.
A33: Control: que no se escape nadie
A34: Al pie de cada cuadre hay cuatro filas encadenadas: B27 Subtotal (suma de los procesos de arriba) + B28 Out of scope (OoS) frente a B29 TOTAL PAYROLL, que suma toda la nómina del negocio y del periodo directamente de la hoja 'Payroll'. B30 es la diferencia sin explicar y debe ser 0.
A35: Si B30 no es 0, hay líneas de nómina que no está recogiendo ninguna fila: normalmente un proceso nuevo que no tiene fila propia, o una persona cuya categoría queda como (unmapped) por un Team o Subproceso que falta en 'Mapping'. La nota del pie indica cuántas filas están sin mapear.
A37: Comentarios y categorías
A38: Comentarios: escribe directamente en la columna O (Comments) de cada hoja de cuadre la justificación de la diferencia. El fichero es de un solo periodo, así que no se guarda histórico: cada mes se parte de un fichero nuevo.
A39: Categorías: AP solo existe dentro del proceso P2P, así que las filas AP se alimentan del mapeo Team → categoría AP y del mapeo Subproceso → categoría AP (tablas de la izquierda de 'Mapping'). En el resto de procesos la categoría es Proceso + Team (por ejemplo Q2C Iberia, R2R Iberia, HR Iberia), usando la tabla Team → etiqueta. Si una persona debe ir en otra categoría, añádela en EXCEPCIONES (columnas G y H de 'Mapping'): manda sobre todo lo demás. El proceso puede venir como 'P2P' o como 'P2P Vuelta': las formulas tratan las dos variantes como P2P (cualquier proceso que empiece por P2P), de modo que esas personas caen en las filas AP igual que el resto.
A41: Notas técnicas
A42: · Las fórmulas usan referencias de columna completa: admiten cualquier número de filas, aumenten o disminuyan.
A43: · La columna K de 'Payroll' está preparada hasta la fila 5000 (unos 30 meses). La nota del pie (A32) avisa si se supera.
A44: · El libro no contiene macros.
